{
  "meta": {
    "title": "Polysemie-Drill — Bedeutung im Kontext",
    "description": "Training zur kontextabhängigen Bedeutungsbestimmung polysemer Wörter im Quran. Der Leser wählt die richtige Bedeutung basierend auf dem Vers-Kontext.",
    "totalEntries": 78,
    "sources": [
      {"title": "Lane's Lexicon", "url": "https://ejtaal.net/aa/"},
      {"title": "Quranic Arabic Corpus", "url": "https://corpus.quran.com/"}
    ]
  },
  "entries": [
    {
      "id": 1,
      "word": "ضَرَبَ",
      "root": "ض-ر-ب",
      "meanings": [
        "schlagen/treffen",
        "prägen/aufstellen",
        "reisen/losziehen",
        "ein Gleichnis anführen",
        "auferlegen"
      ],
      "exercises": [
        {
          "ref": "2:26",
          "arabic": "إِنَّ اللَّهَ لَا يَسْتَحْيِي أَن يَضْرِبَ مَثَلًا",
          "correctMeaning": "ein Gleichnis anführen",
          "context": "Maf'ul bihi ist مَثَلًا (Gleichnis) — das Verb bedeutet hier 'anführen/präsentieren', nicht 'schlagen'."
        },
        {
          "ref": "2:273",
          "arabic": "لَا يَسْتَطِيعُونَ ضَرْبًا فِي الْأَرْضِ",
          "correctMeaning": "reisen/losziehen",
          "context": "ضَرْب فِي الْأَرْضِ = Reisen im Land. Präposition فِي zeigt räumliche Bewegung."
        },
        {
          "ref": "8:12",
          "arabic": "فَاضْرِبُوا فَوْقَ الْأَعْنَاقِ",
          "correctMeaning": "schlagen/treffen",
          "context": "Direkter Imperativ mit Körperteil als Ziel — physisches Schlagen."
        },
        {
          "ref": "43:58",
          "arabic": "مَا ضَرَبُوهُ لَكَ إِلَّا جَدَلًا",
          "correctMeaning": "anführen/vorbringen",
          "context": "Tamyiz جَدَلًا (Streit) zeigt: es geht um Argumentation, nicht physische Handlung."
        }
      ]
    },
    {
      "id": 2,
      "word": "هَدَى",
      "root": "ه-د-ي",
      "meanings": [
        "leiten, den Weg zeigen",
        "Geschenk geben (Opfertier)",
        "den Weg zeigen"
      ],
      "exercises": [
        {
          "ref": "1:6",
          "arabic": "اهْدِنَا الصِّرَاطَ الْمُسْتَقِيمَ",
          "correctMeaning": "leiten, den Weg zeigen",
          "context": "Doppelter Akkusativ (uns + den Weg) — Bitte um Führung."
        },
        {
          "ref": "2:198",
          "arabic": "وَاذْكُرُوهُ كَمَا هَدَاكُمْ",
          "correctMeaning": "den Weg zeigen",
          "context": "كَمَا (so wie) + Pronominalsuffix — Erinnerung an Wegweisung."
        },
        {
          "ref": "2:196",
          "arabic": "فَمَا اسْتَيْسَرَ مِنَ الْهَدْيِ",
          "correctMeaning": "Opfertier (هَدْي)",
          "context": "الْهَدْي = das Opfertier, Nomen von derselben Wurzel ه-د-ي. Hier in der Bedeutung 'Opfergabe', nicht 'Führung'."
        }
      ]
    },
    {
      "id": 3,
      "word": "أَمْر",
      "root": "ا-م-ر",
      "meanings": [
        "Befehl/Anordnung",
        "Angelegenheit/Sache",
        "Entscheidung/Beschluss"
      ],
      "exercises": [
        {
          "ref": "65:5",
          "arabic": "ذَٰلِكَ أَمْرُ اللَّهِ أَنزَلَهُ إِلَيْكُمْ",
          "correctMeaning": "Anordnung/Befehl",
          "context": "أَنزَلَهُ (er sandte es herab) — bezieht sich auf eine herabgesandte Vorschrift."
        },
        {
          "ref": "18:21",
          "arabic": "إِذْ يَتَنَازَعُونَ بَيْنَهُمْ أَمْرَهُمْ",
          "correctMeaning": "Angelegenheit/Sache",
          "context": "يَتَنَازَعُونَ (sie streiten) + بَيْنَهُمْ (untereinander) — es geht um ihre Sache/Angelegenheit."
        },
        {
          "ref": "54:12",
          "arabic": "وَفَجَّرْنَا الْأَرْضَ عُيُونًا فَالْتَقَى الْمَاءُ عَلَىٰ أَمْرٍ قَدْ قُدِرَ",
          "correctMeaning": "Entscheidung/Beschluss",
          "context": "قَدْ قُدِرَ (wurde bestimmt) — vorherbestimmter Beschluss."
        }
      ]
    },
    {
      "id": 4,
      "word": "فَتَنَ",
      "root": "ف-ت-ن",
      "meanings": [
        "prüfen/testen",
        "verfuehren/in Versuchung führen",
        "verfolgen/bedraengen",
        "Zwietracht/Prüfung"
      ],
      "exercises": [
        {
          "ref": "29:2",
          "arabic": "أَحَسِبَ النَّاسُ أَن يُتْرَكُوا أَن يَقُولُوا آمَنَّا وَهُمْ لَا يُفْتَنُونَ",
          "correctMeaning": "geprueft werden",
          "context": "Passiv يُفْتَنُونَ nach Glaubensbekenntnis — Prüfung des Glaubens."
        },
        {
          "ref": "2:191",
          "arabic": "وَالْفِتْنَةُ أَشَدُّ مِنَ الْقَتْلِ",
          "correctMeaning": "Verfolgung/Bedraengnis",
          "context": "Vergleich mit القتل (Toetung) — muss schwerer als Toetung sein: Verfuehrung/Verfolgung/Prüfung."
        },
        {
          "ref": "8:28",
          "arabic": "أَنَّمَا أَمْوَالُكُمْ وَأَوْلَادُكُمْ فِتْنَةٌ",
          "correctMeaning": "Prüfung/Versuchung",
          "context": "Besitz und Kinder als Prüfung — keine Verfolgung, sondern Versuchung."
        }
      ]
    },
    {
      "id": 5,
      "word": "رُوح",
      "root": "ر-و-ح",
      "meanings": [
        "Geist/Seele",
        "Geist/Eingebung",
        "Barmherzigkeit/Trost",
        "Geist der Heiligkeit"
      ],
      "exercises": [
        {
          "ref": "17:85",
          "arabic": "وَيَسْأَلُونَكَ عَنِ الرُّوحِ",
          "correctMeaning": "Geist/Seele",
          "context": "Frage über das Wesen des Ruuh — allgemeine Frage."
        },
        {
          "ref": "16:2",
          "arabic": "يُنَزِّلُ الْمَلَائِكَةَ بِالرُّوحِ مِنْ أَمْرِهِ",
          "correctMeaning": "Geist/Eingebung",
          "context": "بِ + مِنْ أَمْرِهِ — die Engel kommen mit dem Geist aus seinem Befehl."
        },
        {
          "ref": "2:87",
          "arabic": "وَأَيَّدْنَاهُ بِرُوحِ الْقُدُسِ",
          "correctMeaning": "Geist der Heiligkeit",
          "context": "Idafa: رُوحِ الْقُدُسِ = Geist der Heiligkeit/Reinheit. Der Text benennt keinen Eigennamen."
        }
      ]
    },
    {
      "id": 6,
      "word": "آيَة",
      "root": "ا-ي-ي",
      "meanings": [
        "Zeichen/Beweis",
        "Vers (des Quran)",
        "Wunder"
      ],
      "exercises": [
        {
          "ref": "2:106",
          "arabic": "مَا نَنسَخْ مِنْ آيَةٍ أَوْ نُنسِهَا نَأْتِ بِخَيْرٍ مِنْهَا",
          "correctMeaning": "Zeichen/Vers",
          "context": "نَنسَخْ مِنْ آيَةٍ (aufheben von einem Zeichen) — das Wort kann sowohl Zeichen als auch Vers bedeuten."
        },
        {
          "ref": "2:164",
          "arabic": "إِنَّ فِي خَلْقِ السَّمَاوَاتِ وَالْأَرْضِ... لَآيَاتٍ",
          "correctMeaning": "Zeichen/Beweise",
          "context": "Plural آيَات nach Naturphänomenen — beobachtbare Zeichen."
        },
        {
          "ref": "17:101",
          "arabic": "وَلَقَدْ آتَيْنَا مُوسَىٰ تِسْعَ آيَاتٍ بَيِّنَاتٍ",
          "correctMeaning": "Zeichen",
          "context": "تِسْعَ (neun) + بَيِّنَاتٍ (klare) — die neun klaren Zeichen."
        }
      ]
    },
    {
      "id": 7,
      "word": "كَلِمَة",
      "root": "ك-ل-م",
      "meanings": [
        "Wort/Aussage",
        "Versprechen/Dekret",
        "Urteil/Beschluss"
      ],
      "exercises": [
        {
          "ref": "18:109",
          "arabic": "لَوْ كَانَ الْبَحْرُ مِدَادًا لِكَلِمَاتِ رَبِّي",
          "correctMeaning": "Wort/Aussage",
          "context": "مِدَاد (Tinte) — wörtliche Bedeutung: Wörter aufschreiben."
        },
        {
          "ref": "10:33",
          "arabic": "كَذَٰلِكَ حَقَّتْ كَلِمَتُ رَبِّكَ",
          "correctMeaning": "Urteil/Beschluss",
          "context": "حَقَّتْ (hat sich bewahrheitet) — ein Beschluss der in Kraft tritt."
        },
        {
          "ref": "3:45",
          "arabic": "إِنَّ اللَّهَ يُبَشِّرُكِ بِكَلِمَةٍ مِنْهُ اسْمُهُ الْمَسِيحُ",
          "correctMeaning": "Versprechen/Dekret",
          "context": "Ankündigung einer Person mit Namen — كَلِمَة als textuelle Ankündigung."
        }
      ]
    },
    {
      "id": 8,
      "word": "حَقّ",
      "root": "ح-ق-ق",
      "meanings": [
        "Wahrheit",
        "Recht/Anspruch",
        "Pflicht",
        "wahr/berechtigt"
      ],
      "exercises": [
        {
          "ref": "2:147",
          "arabic": "الْحَقُّ مِن رَبِّكَ فَلَا تَكُونَنَّ مِنَ الْمُمْتَرِينَ",
          "correctMeaning": "Wahrheit",
          "context": "Gegensatz zu الْمُمْتَرِينَ (Zweifler) — die Wahrheit."
        },
        {
          "ref": "6:141",
          "arabic": "وَآتُوا حَقَّهُ يَوْمَ حَصَادِهِ",
          "correctMeaning": "Recht/Anspruch (Abgabe)",
          "context": "يَوْمَ حَصَادِهِ (am Tag der Ernte) — pflichtiger Anteil."
        },
        {
          "ref": "36:7",
          "arabic": "لَقَدْ حَقَّ الْقَوْلُ عَلَىٰ أَكْثَرِهِمْ",
          "correctMeaning": "sich bewahrheiten/in Kraft treten",
          "context": "Verb حَقَّ + عَلَى — das Urteil hat sich an ihnen erfüllt."
        }
      ]
    },
    {
      "id": 9,
      "word": "دِين",
      "root": "د-ي-ن",
      "meanings": [
        "Religion/Lebensweise",
        "Gericht/Abrechnung",
        "Schuld"
      ],
      "exercises": [
        {
          "ref": "109:6",
          "arabic": "لَكُمْ دِينُكُمْ وَلِيَ دِينِ",
          "correctMeaning": "Religion/Lebensweise",
          "context": "Kontrastierung zweier Lebensweisen — eure und meine."
        },
        {
          "ref": "1:4",
          "arabic": "مَالِكِ يَوْمِ الدِّينِ",
          "correctMeaning": "Gericht/Abrechnung",
          "context": "يَوْم (Tag) + Idafa — der Tag der Abrechnung."
        },
        {
          "ref": "2:282",
          "arabic": "إِذَا تَدَايَنتُم بِدَيْنٍ",
          "correctMeaning": "Schuld",
          "context": "تَدَايَنتُم (ihr schuldet einander) — finanzieller Kontext."
        }
      ]
    },
    {
      "id": 10,
      "word": "سَبِيل",
      "root": "س-ب-ل",
      "meanings": [
        "Weg/Pfad",
        "Sache/Zweck (fi sabil Allah)",
        "Mittel/Möglichkeit"
      ],
      "exercises": [
        {
          "ref": "2:154",
          "arabic": "وَلَا تَقُولُوا لِمَن يُقْتَلُ فِي سَبِيلِ اللَّهِ",
          "correctMeaning": "Sache/Zweck",
          "context": "فِي سَبِيلِ اللَّهِ — feste Wendung: für die Sache Gottes."
        },
        {
          "ref": "25:27",
          "arabic": "يَا لَيْتَنِي اتَّخَذْتُ مَعَ الرَّسُولِ سَبِيلًا",
          "correctMeaning": "Weg/Pfad",
          "context": "اتَّخَذْتُ (ich hätte genommen) — einen Weg eingeschlagen."
        },
        {
          "ref": "4:141",
          "arabic": "فَلَن يَجْعَلَ اللَّهُ لِلْكَافِرِينَ عَلَى الْمُؤْمِنِينَ سَبِيلًا",
          "correctMeaning": "Mittel/Möglichkeit",
          "context": "عَلَى (gegen) — kein Mittel/Zugang gegen die Gläubigen."
        }
      ]
    },
    {
      "id": 11,
      "word": "فَتَحَ",
      "root": "ف-ت-ح",
      "meanings": [
        "öffnen",
        "erobern/zum Sieg führen",
        "entscheiden/richten"
      ],
      "exercises": [
        {
          "ref": "54:11",
          "arabic": "فَفَتَحْنَا أَبْوَابَ السَّمَاءِ",
          "correctMeaning": "öffnen",
          "context": "أَبْوَاب (Tore) — wörtliches Öffnen."
        },
        {
          "ref": "48:1",
          "arabic": "إِنَّا فَتَحْنَا لَكَ فَتْحًا مُبِينًا",
          "correctMeaning": "Sieg/Eroberung",
          "context": "Maf'ul mutlaq فَتْحًا مُبِينًا — ein klarer Sieg."
        },
        {
          "ref": "7:89",
          "arabic": "رَبَّنَا افْتَحْ بَيْنَنَا وَبَيْنَ قَوْمِنَا بِالْحَقِّ",
          "correctMeaning": "entscheiden/richten",
          "context": "بَيْنَنَا وَبَيْنَ (zwischen uns und) — Bitte um ein Urteil."
        }
      ]
    },
    {
      "id": 12,
      "word": "بَلَاء",
      "root": "ب-ل-و",
      "meanings": [
        "Prüfung/Test",
        "Gnade/Wohltat",
        "Leid/Unglück"
      ],
      "exercises": [
        {
          "ref": "2:49",
          "arabic": "وَفِي ذَٰلِكُم بَلَاءٌ مِنْ رَبِّكُمْ عَظِيمٌ",
          "correctMeaning": "Prüfung",
          "context": "Nach Rettung und Bestrafung — beides war eine grosse Prüfung."
        },
        {
          "ref": "8:17",
          "arabic": "وَلِيُبْلِيَ الْمُؤْمِنِينَ مِنْهُ بَلَاءً حَسَنًا",
          "correctMeaning": "Gnade/Wohltat",
          "context": "حَسَنًا (gut/schön) — eine gute Gabe, Gnade."
        },
        {
          "ref": "44:33",
          "arabic": "وَآتَيْنَاهُم مِنَ الْآيَاتِ مَا فِيهِ بَلَاءٌ مُبِينٌ",
          "correctMeaning": "Prüfung",
          "context": "مُبِينٌ (klar/deutlich) + Zeichen — deutliche Prüfung."
        }
      ]
    },
    {
      "id": 13,
      "word": "وَلِيّ",
      "root": "و-ل-ي",
      "meanings": [
        "Schutzherr/Beschuetzer",
        "Freund/Verbuendeter",
        "Naher/Zuständiger"
      ],
      "exercises": [
        {
          "ref": "2:257",
          "arabic": "اللَّهُ وَلِيُّ الَّذِينَ آمَنُوا",
          "correctMeaning": "Schutzherr/Beschuetzer",
          "context": "Idafa mit الَّذِينَ آمَنُوا — Gott als Beschuetzer der Gläubigen."
        },
        {
          "ref": "45:19",
          "arabic": "إِنَّهُمْ لَن يُغْنُوا عَنكَ مِنَ اللَّهِ شَيْئًا وَإِنَّ الظَّالِمِينَ بَعْضُهُمْ أَوْلِيَاءُ بَعْضٍ",
          "correctMeaning": "Verbuendeter/Freund",
          "context": "بَعْضُهُمْ ... بَعْضٍ (einander) — gegenseitige Allianz."
        },
        {
          "ref": "19:5",
          "arabic": "وَإِنِّي خِفْتُ الْمَوَالِيَ مِن وَرَائِي",
          "correctMeaning": "Naher/Verwandter",
          "context": "مِن وَرَائِي (nach mir) — Verwandte als Erben."
        }
      ]
    },
    {
      "id": 14,
      "word": "سُلْطَان",
      "root": "س-ل-ط",
      "meanings": [
        "Beweis/Beweiskraft",
        "Macht/Autorität",
        "Ermächtigung"
      ],
      "exercises": [
        {
          "ref": "7:71",
          "arabic": "أَتُجَادِلُونَنِي فِي أَسْمَاءٍ... مَا نَزَّلَ اللَّهُ بِهَا مِن سُلْطَانٍ",
          "correctMeaning": "Beweis/Beweiskraft",
          "context": "نَزَّلَ (herabgesandt) + Negation مَا — kein Beweis wurde herabgesandt."
        },
        {
          "ref": "14:22",
          "arabic": "وَمَا كَانَ لِيَ عَلَيْكُم مِن سُلْطَانٍ",
          "correctMeaning": "Macht/Autorität",
          "context": "عَلَيْكُمْ (über euch) — keine Gewalt über euch."
        },
        {
          "ref": "17:33",
          "arabic": "فَقَدْ جَعَلْنَا لِوَلِيِّهِ سُلْطَانًا",
          "correctMeaning": "Ermächtigung",
          "context": "جَعَلْنَا لِـ (wir gaben dem) — rechtliche Ermächtigung."
        }
      ]
    },
    {
      "id": 15,
      "word": "كِتَاب",
      "root": "ك-ت-ب",
      "meanings": [
        "Buch/Schrift",
        "Vorschrift/Verordnung",
        "Schicksal/Bestimmung"
      ],
      "exercises": [
        {
          "ref": "2:2",
          "arabic": "ذَٰلِكَ الْكِتَابُ لَا رَيْبَ فِيهِ",
          "correctMeaning": "Buch/Schrift",
          "context": "Verweis auf den Quran als Text."
        },
        {
          "ref": "2:235",
          "arabic": "حَتَّىٰ يَبْلُغَ الْكِتَابُ أَجَلَهُ",
          "correctMeaning": "Vorschrift/Verordnung",
          "context": "أَجَلَهُ (seine Frist) — die vorgeschriebene Wartezeit."
        },
        {
          "ref": "3:145",
          "arabic": "وَمَا كَانَ لِنَفْسٍ أَن تَمُوتَ إِلَّا بِإِذْنِ اللَّهِ كِتَابًا مُّؤَجَّلًا",
          "correctMeaning": "Schicksal/Bestimmung",
          "context": "كِتَابًا مُّؤَجَّلًا — als festgesetzte Bestimmung. Akkusativ als Hal oder Maf'ul mutlaq."
        }
      ]
    },
    {
      "id": 16,
      "word": "فَضْل",
      "root": "ف-ض-ل",
      "meanings": [
        "Gnade/Gunst",
        "Überschuss/Überfluss",
        "Vorzug/Überlegenheit"
      ],
      "exercises": [
        {
          "ref": "2:198",
          "arabic": "لَيْسَ عَلَيْكُمْ جُنَاحٌ أَن تَبْتَغُوا فَضْلًا مِنْ رَبِّكُمْ",
          "correctMeaning": "Gnade/Gunst (Lebensunterhalt)",
          "context": "تَبْتَغُوا (ihr sucht) + مِنْ رَبِّكُمْ — Erwerb als Gnade Gottes."
        },
        {
          "ref": "2:253",
          "arabic": "فَضَّلْنَا بَعْضَهُمْ عَلَىٰ بَعْضٍ",
          "correctMeaning": "Vorzug geben",
          "context": "بَعْضَ ... عَلَىٰ بَعْضٍ — einige über andere bevorzugen."
        },
        {
          "ref": "57:21",
          "arabic": "ذَٰلِكَ فَضْلُ اللَّهِ يُؤْتِيهِ مَن يَشَاءُ",
          "correctMeaning": "Gnade/Gunst",
          "context": "يُؤْتِيهِ (er gibt es) — frei gegebene Gnade."
        }
      ]
    },
    {
      "id": 17,
      "word": "نَفْس",
      "root": "ن-ف-س",
      "meanings": [
        "Seele/Selbst",
        "Person/Mensch",
        "inneres Wesen"
      ],
      "exercises": [
        {
          "ref": "91:7",
          "arabic": "وَنَفْسٍ وَمَا سَوَّاهَا",
          "correctMeaning": "Seele/inneres Wesen",
          "context": "Schwurformel + سَوَّاهَا (er formte sie) — die innere Natur."
        },
        {
          "ref": "5:32",
          "arabic": "مَن قَتَلَ نَفْسًا بِغَيْرِ نَفْسٍ",
          "correctMeaning": "Person/Mensch",
          "context": "قَتَلَ (töten) — eine Person töten."
        },
        {
          "ref": "12:53",
          "arabic": "وَمَا أُبَرِّئُ نَفْسِي إِنَّ النَّفْسَ لَأَمَّارَةٌ بِالسُّوءِ",
          "correctMeaning": "Seele/Selbst",
          "context": "أُبَرِّئُ (freisprechen) — das eigene Selbst/die Triebseele."
        }
      ]
    },
    {
      "id": 18,
      "word": "عَيْن",
      "root": "ع-ي-ن",
      "meanings": [
        "Auge",
        "Quelle/Wasserquelle",
        "Wesensgleich/selbst"
      ],
      "exercises": [
        {
          "ref": "54:14",
          "arabic": "تَجْرِي بِأَعْيُنِنَا",
          "correctMeaning": "unter Unserer Aufsicht",
          "context": "تَجْرِي (sie läuft/faehrt) — die Arche faehrt unter Gottes Augen/Aufsicht."
        },
        {
          "ref": "2:60",
          "arabic": "فَانفَجَرَتْ مِنْهُ اثْنَتَا عَشْرَةَ عَيْنًا",
          "correctMeaning": "Quelle/Wasserquelle",
          "context": "اِنفَجَرَتْ (brach hervor) — Wasserquellen."
        },
        {
          "ref": "20:39",
          "arabic": "وَلِتُصْنَعَ عَلَىٰ عَيْنِي",
          "correctMeaning": "unter Meiner Aufsicht",
          "context": "عَلَى + Pronominalsuffix — unter Gottes direkter Obhut."
        }
      ]
    },
    {
      "id": 19,
      "word": "جَعَلَ",
      "root": "ج-ع-ل",
      "meanings": [
        "machen/erschaffen",
        "einsetzen/bestimmen",
        "beginnen (mit Imperfekt)"
      ],
      "exercises": [
        {
          "ref": "2:22",
          "arabic": "الَّذِي جَعَلَ لَكُمُ الْأَرْضَ فِرَاشًا",
          "correctMeaning": "machen zu/einrichten als",
          "context": "Doppelter Akkusativ: الْأَرْضَ + فِرَاشًا — die Erde zu einem Lager machen."
        },
        {
          "ref": "2:143",
          "arabic": "وَكَذَٰلِكَ جَعَلْنَاكُمْ أُمَّةً وَسَطًا",
          "correctMeaning": "einsetzen/bestimmen",
          "context": "Doppelter Akkusativ: كُمْ + أُمَّةً — euch zu einer Gemeinschaft bestimmen."
        },
        {
          "ref": "6:1",
          "arabic": "وَجَعَلَ الظُّلُمَاتِ وَالنُّورَ",
          "correctMeaning": "machen/bewirken",
          "context": "جَعَلَ + Akkusativ — erschaffen/hervorbringen von Finsternis und Licht."
        }
      ]
    },
    {
      "id": 20,
      "word": "قَدَرَ",
      "root": "ق-د-ر",
      "meanings": [
        "bestimmen/vorherbestimmen",
        "fähig sein/vermögen",
        "eng machen/bemessen"
      ],
      "exercises": [
        {
          "ref": "54:49",
          "arabic": "إِنَّا كُلَّ شَيْءٍ خَلَقْنَاهُ بِقَدَرٍ",
          "correctMeaning": "Bestimmung/Mass",
          "context": "بِقَدَرٍ (nach einem Mass) — vorherbestimmte Ordnung."
        },
        {
          "ref": "2:236",
          "arabic": "عَلَى الْمُوسِعِ قَدَرُهُ وَعَلَى الْمُقْتِرِ قَدَرُهُ",
          "correctMeaning": "bemessener Anteil",
          "context": "الْمُوسِع vs. الْمُقْتِر (der Wohlhabende vs. der Beschränkte) — nach Vermögen."
        },
        {
          "ref": "36:81",
          "arabic": "أَوَلَيْسَ الَّذِي خَلَقَ السَّمَاوَاتِ وَالْأَرْضَ بِقَادِرٍ",
          "correctMeaning": "fähig sein",
          "context": "Partizip قَادِر — Fähigkeit zur Neuerschaffung."
        }
      ]
    },
    {
      "id": 21,
      "word": "ظَنَّ",
      "root": "ظ-ن-ن",
      "meanings": [
        "vermuten/annehmen",
        "sicher sein/ueberzeugt sein"
      ],
      "exercises": [
        {
          "ref": "2:46",
          "arabic": "الَّذِينَ يَظُنُّونَ أَنَّهُم مُلَاقُو رَبِّهِمْ",
          "correctMeaning": "sicher sein/ueberzeugt sein",
          "context": "مُلَاقُو رَبِّهِمْ (Gott begegnen werden) — positiver Kontext, Gewissheit."
        },
        {
          "ref": "49:12",
          "arabic": "اجْتَنِبُوا كَثِيرًا مِنَ الظَّنِّ إِنَّ بَعْضَ الظَّنِّ إِثْمٌ",
          "correctMeaning": "Vermutung/Annahme",
          "context": "إِثْمٌ (Sünde) — unbelegte Vermutung ist suendhaft."
        }
      ]
    },
    {
      "id": 22,
      "word": "مَثَل",
      "root": "م-ث-ل",
      "meanings": [
        "Gleichnis/Parabel",
        "Eigenschaft/Beschaffenheit",
        "Beispiel"
      ],
      "exercises": [
        {
          "ref": "2:17",
          "arabic": "مَثَلُهُمْ كَمَثَلِ الَّذِي اسْتَوْقَدَ نَارًا",
          "correctMeaning": "Gleichnis",
          "context": "كَـ (wie) — expliziter Vergleich, Parabel."
        },
        {
          "ref": "47:15",
          "arabic": "مَثَلُ الْجَنَّةِ الَّتِي وُعِدَ الْمُتَّقُونَ",
          "correctMeaning": "Beschaffenheit/Beschreibung",
          "context": "Keine Vergleichspartikel — Beschreibung des Paradieses."
        },
        {
          "ref": "14:45",
          "arabic": "وَقَدْ ضَرَبْنَا لَكُمُ الْأَمْثَالَ",
          "correctMeaning": "Beispiele",
          "context": "ضَرَبَ (anführen) — Beispiele zur Belehrung."
        }
      ]
    },
    {
      "id": 23,
      "word": "عَرَضَ",
      "root": "ع-ر-ض",
      "meanings": [
        "vorzeigen/präsentieren",
        "vorbeigehen/sich abwenden",
        "Gebrauchsgut/vergängliches Gut"
      ],
      "exercises": [
        {
          "ref": "2:31",
          "arabic": "ثُمَّ عَرَضَهُمْ عَلَى الْمَلَائِكَةِ",
          "correctMeaning": "vorzeigen/präsentieren",
          "context": "عَلَى (den Engeln) — Präsentation vor den Engeln."
        },
        {
          "ref": "7:46",
          "arabic": "وَعَلَى الْأَعْرَافِ رِجَالٌ يَعْرِفُونَ كُلًّا بِسِيمَاهُمْ",
          "correctMeaning": "die Erhöhungen / die Anhoehen",
          "context": "الْأَعْرَاف (die Erhöhungen, Plural von عُرْف) — räumlich erhöhte Position. Verwandte Wurzel ع-ر-ف, hier als Ortsbezeichnung."
        },
        {
          "ref": "8:67",
          "arabic": "تُرِيدُونَ عَرَضَ الدُّنْيَا",
          "correctMeaning": "vergängliches Gut",
          "context": "الدُّنْيَا (das Diesseits) — vergängliche Güter."
        }
      ]
    },
    {
      "id": 24,
      "word": "بَصِيرَة",
      "root": "ب-ص-ر",
      "meanings": [
        "Einsicht/inneres Sehen",
        "Beweis/Evidenz",
        "Sehkraft"
      ],
      "exercises": [
        {
          "ref": "12:108",
          "arabic": "قُلْ هَٰذِهِ سَبِيلِي أَدْعُو إِلَى اللَّهِ عَلَىٰ بَصِيرَةٍ",
          "correctMeaning": "Einsicht/Klarheit",
          "context": "عَلَىٰ (auf der Grundlage von) — auf Basis klarer Einsicht."
        },
        {
          "ref": "75:14",
          "arabic": "بَلِ الْإِنسَانُ عَلَىٰ نَفْسِهِ بَصِيرَةٌ",
          "correctMeaning": "Zeuge/Beweis gegen sich selbst",
          "context": "عَلَى نَفْسِهِ — der Mensch ist Beweis gegen sich selbst."
        }
      ]
    },
    {
      "id": 25,
      "word": "نُور",
      "root": "ن-و-ر",
      "meanings": [
        "Licht (physisch)",
        "Führung/Erhellung",
        "Schrift/Führung"
      ],
      "exercises": [
        {
          "ref": "24:35",
          "arabic": "اللَّهُ نُورُ السَّمَاوَاتِ وَالْأَرْضِ",
          "correctMeaning": "Licht/Erhellung",
          "context": "Idafa — Gott als Licht von Himmel und Erde."
        },
        {
          "ref": "5:15",
          "arabic": "قَدْ جَاءَكُم مِنَ اللَّهِ نُورٌ وَكِتَابٌ مُبِينٌ",
          "correctMeaning": "Schrift/Führung",
          "context": "Koordiniert mit كِتَاب — Licht als Metapher für die Schrift."
        },
        {
          "ref": "57:12",
          "arabic": "يَسْعَىٰ نُورُهُم بَيْنَ أَيْدِيهِمْ",
          "correctMeaning": "Licht (eschatologisch)",
          "context": "يَسْعَى (eilt voraus) + بَيْنَ أَيْدِيهِمْ — ein Licht das vor ihnen hergeht."
        }
      ]
    },
    {
      "id": 26,
      "word": "مَكْر",
      "root": "م-ك-ر",
      "meanings": [
        "List/Plan (negativ)",
        "Planung/Strategie (neutral)",
        "Gegenstrategie"
      ],
      "exercises": [
        {
          "ref": "3:54",
          "arabic": "وَمَكَرُوا وَمَكَرَ اللَّهُ وَاللَّهُ خَيْرُ الْمَاكِرِينَ",
          "correctMeaning": "Plan/Gegenstrategie",
          "context": "Parallelismus: sie planten — Gott plante dagegen. خَيْرُ zeigt: keine negative Konnotation bei Gott."
        },
        {
          "ref": "10:21",
          "arabic": "لَهُ مَكْرٌ فِي الْبَرِّ وَالْبَحْرِ",
          "correctMeaning": "List/Täuschung",
          "context": "Im Kontext menschlicher Bosheit."
        }
      ]
    },
    {
      "id": 27,
      "word": "غَيْب",
      "root": "غ-ي-ب",
      "meanings": [
        "Verborgenes/Unsichtbares",
        "Abwesenheit",
        "unzugaengliches Wissen"
      ],
      "exercises": [
        {
          "ref": "2:3",
          "arabic": "الَّذِينَ يُؤْمِنُونَ بِالْغَيْبِ",
          "correctMeaning": "das Verborgene/Unsichtbare",
          "context": "يُؤْمِنُونَ بِـ (glauben an) — Glaube an das Unsichtbare."
        },
        {
          "ref": "12:52",
          "arabic": "ذَٰلِكَ لِيَعْلَمَ أَنِّي لَمْ أَخُنْهُ بِالْغَيْبِ",
          "correctMeaning": "in seiner Abwesenheit",
          "context": "لَمْ أَخُنْهُ (ich habe ihn nicht verraten) — während seiner Abwesenheit."
        },
        {
          "ref": "6:59",
          "arabic": "وَعِندَهُ مَفَاتِحُ الْغَيْبِ لَا يَعْلَمُهَا إِلَّا هُوَ",
          "correctMeaning": "unzugaengliches Wissen",
          "context": "مَفَاتِحُ (Schlüssel) — Zugang zu verborgenem Wissen."
        }
      ]
    },
    {
      "id": 28,
      "word": "بَعَثَ",
      "root": "ب-ع-ث",
      "meanings": [
        "auferwecken (von den Toten)",
        "entsenden/schicken",
        "erwecken/veranlassen"
      ],
      "exercises": [
        {
          "ref": "22:7",
          "arabic": "وَأَنَّ اللَّهَ يَبْعَثُ مَن فِي الْقُبُورِ",
          "correctMeaning": "auferwecken",
          "context": "مَن فِي الْقُبُورِ (die in den Graebern) — Auferweckung der Toten."
        },
        {
          "ref": "2:129",
          "arabic": "رَبَّنَا وَابْعَثْ فِيهِمْ رَسُولًا مِنْهُمْ",
          "correctMeaning": "entsenden/schicken",
          "context": "رَسُولًا (einen Gesandten) — Sendung eines Propheten."
        },
        {
          "ref": "17:79",
          "arabic": "عَسَىٰ أَن يَبْعَثَكَ رَبُّكَ مَقَامًا مَحْمُودًا",
          "correctMeaning": "erheben/erwecken zu",
          "context": "مَقَامًا مَحْمُودًا (eine gelobte Stellung) — Erhebung zu einer Position."
        }
      ]
    },
    {
      "id": 29,
      "word": "أُمَّة",
      "root": "ا-م-م",
      "meanings": [
        "Gemeinschaft/Volk",
        "Zeitspanne",
        "Vorbild/Anführer",
        "Religion/Glaubensrichtung"
      ],
      "exercises": [
        {
          "ref": "2:143",
          "arabic": "وَكَذَٰلِكَ جَعَلْنَاكُمْ أُمَّةً وَسَطًا",
          "correctMeaning": "Gemeinschaft/Volk",
          "context": "وَسَطًا (mittlere/gerechte) beschreibt eine Gruppe — Gemeinschaft."
        },
        {
          "ref": "12:45",
          "arabic": "وَادَّكَرَ بَعْدَ أُمَّةٍ",
          "correctMeaning": "Zeitspanne",
          "context": "بَعْدَ (nach) + أُمَّةٍ — er erinnerte sich nach einer langen Zeitspanne."
        },
        {
          "ref": "16:120",
          "arabic": "إِنَّ إِبْرَاهِيمَ كَانَ أُمَّةً قَانِتًا لِلَّهِ",
          "correctMeaning": "Vorbild/Anführer",
          "context": "Ein Einzelner (Ibrahim) wird als أُمَّة bezeichnet — er allein war ein Vorbild/eine ganze Institution."
        },
        {
          "ref": "43:22",
          "arabic": "إِنَّا وَجَدْنَا آبَاءَنَا عَلَىٰ أُمَّةٍ",
          "correctMeaning": "Religion/Glaubensrichtung",
          "context": "عَلَىٰ (auf) — sie fanden ihre Vaeter auf einer bestimmten Glaubensrichtung."
        }
      ]
    },
    {
      "id": 30,
      "word": "شَهِيد",
      "root": "ش-ه-د",
      "meanings": [
        "Zeuge",
        "Beobachter/Wachender",
        "Zeuge (im Kampfkontext)"
      ],
      "exercises": [
        {
          "ref": "2:143",
          "arabic": "وَيَكُونَ الرَّسُولُ عَلَيْكُمْ شَهِيدًا",
          "correctMeaning": "Zeuge",
          "context": "Der Gesandte bezeugt über die Gemeinschaft — Zeugenfunktion."
        },
        {
          "ref": "4:166",
          "arabic": "لَٰكِنِ اللَّهُ يَشْهَدُ بِمَا أَنزَلَ إِلَيْكَ",
          "correctMeaning": "Zeuge/Bezeugender",
          "context": "Gott bezeugt die Herabsendung — Bestätigungsfunktion."
        },
        {
          "ref": "3:140",
          "arabic": "وَيَتَّخِذَ مِنكُمْ شُهَدَاءَ",
          "correctMeaning": "Zeuge (im Kampfkontext)",
          "context": "Kontext des Kampfes (قَاتَلُوا/قُتِلُوا) — Gott nimmt sich Zeugen aus den Kämpfenden."
        },
        {
          "ref": "5:117",
          "arabic": "وَكُنتُ عَلَيْهِمْ شَهِيدًا مَا دُمْتُ فِيهِمْ",
          "correctMeaning": "Beobachter/Wachender",
          "context": "مَا دُمْتُ فِيهِمْ (solange ich unter ihnen war) — Aufsicht/Beobachtung."
        }
      ]
    },
    {
      "id": 31,
      "word": "فُرْقَان",
      "root": "ف-ر-ق",
      "meanings": [
        "Unterscheidungskriterium",
        "Rettung/Befreiung",
        "die Schrift/Unterscheidungsschrift"
      ],
      "exercises": [
        {
          "ref": "2:53",
          "arabic": "وَإِذْ آتَيْنَا مُوسَى الْكِتَابَ وَالْفُرْقَانَ",
          "correctMeaning": "Unterscheidungskriterium",
          "context": "Zusammen mit الْكِتَاب genannt — das Kriterium zur Unterscheidung von Recht und Unrecht."
        },
        {
          "ref": "8:29",
          "arabic": "إِن تَتَّقُوا اللَّهَ يَجْعَل لَّكُمْ فُرْقَانًا",
          "correctMeaning": "Rettung/Ausweg",
          "context": "Konditional mit تَتَّقُوا — als Resultat der Achtsamkeit wird ein Ausweg/eine Rettung gewährt."
        },
        {
          "ref": "25:1",
          "arabic": "تَبَارَكَ الَّذِي نَزَّلَ الْفُرْقَانَ عَلَىٰ عَبْدِهِ",
          "correctMeaning": "die Unterscheidungsschrift",
          "context": "نَزَّلَ (herabgesandt) + عَلَىٰ عَبْدِهِ — Bezeichnung für die herabgesandte Schrift."
        }
      ]
    },
    {
      "id": 32,
      "word": "ذِكْر",
      "root": "ذ-ك-ر",
      "meanings": [
        "Erinnerung/Gedenken",
        "Ermahnung/Botschaft",
        "Ruhm/Ansehen",
        "Erwähnung"
      ],
      "exercises": [
        {
          "ref": "13:28",
          "arabic": "أَلَا بِذِكْرِ اللَّهِ تَطْمَئِنُّ الْقُلُوبُ",
          "correctMeaning": "Gedenken/Erinnerung",
          "context": "تَطْمَئِنُّ الْقُلُوبُ (die Herzen finden Ruhe) — durch das Gedenken an Gott."
        },
        {
          "ref": "15:9",
          "arabic": "إِنَّا نَحْنُ نَزَّلْنَا الذِّكْرَ وَإِنَّا لَهُ لَحَافِظُونَ",
          "correctMeaning": "Ermahnung/Botschaft (Quran)",
          "context": "نَزَّلْنَا (wir sandten herab) — bezeichnet die herabgesandte Botschaft."
        },
        {
          "ref": "21:10",
          "arabic": "لَقَدْ أَنزَلْنَا إِلَيْكُمْ كِتَابًا فِيهِ ذِكْرُكُمْ",
          "correctMeaning": "Ruhm/Ansehen",
          "context": "ذِكْرُكُمْ (euer Ruhm/eure Erwähnung) — das Buch enthält ihren Ruhm."
        },
        {
          "ref": "38:32",
          "arabic": "فَقَالَ إِنِّي أَحْبَبْتُ حُبَّ الْخَيْرِ عَن ذِكْرِ رَبِّي",
          "correctMeaning": "Erinnerung/Gedenken",
          "context": "عَن ذِكْرِ رَبِّي — er wurde vom Gedenken an seinen Herrn abgelenkt."
        }
      ]
    },
    {
      "id": 33,
      "word": "حِكْمَة",
      "root": "ح-ك-م",
      "meanings": [
        "Weisheit",
        "Urteilsvermoegen",
        "Prophetie/Schrift"
      ],
      "exercises": [
        {
          "ref": "2:269",
          "arabic": "يُؤْتِي الْحِكْمَةَ مَن يَشَاءُ",
          "correctMeaning": "Weisheit",
          "context": "يُؤْتِي (er gibt) + مَن يَشَاءُ (wem er will) — allgemeine Gabe der Weisheit."
        },
        {
          "ref": "3:48",
          "arabic": "وَيُعَلِّمُهُ الْكِتَابَ وَالْحِكْمَةَ وَالتَّوْرَاةَ وَالْإِنجِيلَ",
          "correctMeaning": "Prophetie/Schrift",
          "context": "Aufzählung neben الْكِتَاب und التَّوْرَاة — prophetisches Wissen."
        },
        {
          "ref": "31:12",
          "arabic": "وَلَقَدْ آتَيْنَا لُقْمَانَ الْحِكْمَةَ",
          "correctMeaning": "Urteilsvermoegen",
          "context": "Luqman ist kein Prophet — ihm wird حِكْمَة als gutes Urteilsvermoegen gegeben."
        }
      ]
    },
    {
      "id": 34,
      "word": "صَلَاة",
      "root": "ص-ل-و",
      "meanings": [
        "Gebet/Hinwendung",
        "Segen/Segenswunsch",
        "Hinwendung/Zuwendung"
      ],
      "exercises": [
        {
          "ref": "2:43",
          "arabic": "وَأَقِيمُوا الصَّلَاةَ وَآتُوا الزَّكَاةَ",
          "correctMeaning": "Gebet/Hinwendung",
          "context": "أَقِيمُوا (richtet auf/erhaltet aufrecht) — Aufforderung zum Gebet, parallel zur Zakaat."
        },
        {
          "ref": "33:56",
          "arabic": "إِنَّ اللَّهَ وَمَلَائِكَتَهُ يُصَلُّونَ عَلَى النَّبِيِّ",
          "correctMeaning": "Segen/Segenswunsch",
          "context": "يُصَلُّونَ عَلَى النَّبِيِّ bedeutet 'Segen sprechen' — der Textsprecher und Engel wenden sich dem Nabi zu, nicht 'beten'."
        },
        {
          "ref": "9:103",
          "arabic": "وَصَلِّ عَلَيْهِمْ إِنَّ صَلَاتَكَ سَكَنٌ لَّهُمْ",
          "correctMeaning": "Zuwendung/Fuerbitten",
          "context": "سَكَنٌ لَّهُمْ (Beruhigung für sie) — صَلَاتَكَ (deine Zuwendung) beruhigt die Angesprochenen."
        }
      ]
    },
    {
      "id": 35,
      "word": "فِطْرَة",
      "root": "ف-ط-ر",
      "meanings": [
        "natuerliche Anlage/Urnatur",
        "Schöpfungsart",
        "Spaltung/Bruch"
      ],
      "exercises": [
        {
          "ref": "30:30",
          "arabic": "فِطْرَتَ اللَّهِ الَّتِي فَطَرَ النَّاسَ عَلَيْهَا",
          "correctMeaning": "natuerliche Anlage/Urnatur",
          "context": "فَطَرَ النَّاسَ عَلَيْهَا (auf der er die Menschen erschuf) — angeborene Veranlagung."
        },
        {
          "ref": "6:79",
          "arabic": "إِنِّي وَجَّهْتُ وَجْهِيَ لِلَّذِي فَطَرَ السَّمَاوَاتِ وَالْأَرْضَ",
          "correctMeaning": "erschaffen/ins Dasein bringen",
          "context": "فَطَرَ السَّمَاوَاتِ (er spaltete/erschuf die Himmel) — Schöpfungsakt."
        },
        {
          "ref": "82:1",
          "arabic": "إِذَا السَّمَاءُ انفَطَرَتْ",
          "correctMeaning": "sich spalten/brechen",
          "context": "انفَطَرَتْ (VII. Stamm — reflexiv) — der Himmel spaltet sich."
        }
      ]
    },
    {
      "id": 36,
      "word": "خَلِيفَة",
      "root": "خ-ل-ف",
      "meanings": [
        "Nachfolger/Nachfolgend",
        "Stellvertreter",
        "Bevollmächtigter auf Erden"
      ],
      "exercises": [
        {
          "ref": "2:30",
          "arabic": "إِنِّي جَاعِلٌ فِي الْأَرْضِ خَلِيفَةً",
          "correctMeaning": "Nachfolger/Nachfolgend",
          "context": "فِي الْأَرْضِ — einer, der auf der Erde nachfolgt (auf fruehere Wesen)."
        },
        {
          "ref": "38:26",
          "arabic": "يَا دَاوُودُ إِنَّا جَعَلْنَاكَ خَلِيفَةً فِي الْأَرْضِ",
          "correctMeaning": "Bevollmächtigter/Herrscher auf Erden",
          "context": "Dawud als König — er soll auf Erden richten (فَاحْكُم بَيْنَ النَّاسِ)."
        },
        {
          "ref": "6:165",
          "arabic": "وَهُوَ الَّذِي جَعَلَكُمْ خَلَائِفَ الْأَرْضِ",
          "correctMeaning": "Nachfolger (aufeinanderfolgend)",
          "context": "Plural خَلَائِف — aufeinanderfolgende Generationen auf der Erde."
        }
      ]
    },
    {
      "id": 37,
      "word": "رَحْمَة",
      "root": "ر-ح-م",
      "meanings": [
        "Barmherzigkeit/Gnade",
        "Regen/Versorgung",
        "Gnade/Barmherzigkeit (erweitert)"
      ],
      "exercises": [
        {
          "ref": "2:157",
          "arabic": "أُولَٰئِكَ عَلَيْهِمْ صَلَوَاتٌ مِّن رَّبِّهِمْ وَرَحْمَةٌ",
          "correctMeaning": "Barmherzigkeit/Gnade",
          "context": "Von dem Herrn kommend für die Geduldigen — رَحْمَة als Zuwendung im Text."
        },
        {
          "ref": "30:46",
          "arabic": "وَلِيُذِيقَكُم مِّن رَّحْمَتِهِ وَلِتَجْرِيَ الْفُلْكُ بِأَمْرِهِ",
          "correctMeaning": "Regen/guenstiger Wind",
          "context": "لِتَجْرِيَ الْفُلْكُ (damit die Schiffe fahren) — die رَحْمَة hier sind guenstige Winde/Regen."
        },
        {
          "ref": "21:107",
          "arabic": "وَمَا أَرْسَلْنَاكَ إِلَّا رَحْمَةً لِّلْعَالَمِينَ",
          "correctMeaning": "Barmherzigkeit (personifiziert)",
          "context": "Der Gesandte selbst wird als رَحْمَة für die Welten bezeichnet."
        },
        {
          "ref": "43:32",
          "arabic": "أَهُمْ يَقْسِمُونَ رَحْمَتَ رَبِّكَ",
          "correctMeaning": "Gabe/Versorgung",
          "context": "يَقْسِمُونَ (verteilen sie?) — Gottes Gaben können nicht von Menschen aufgeteilt werden."
        }
      ]
    },
    {
      "id": 38,
      "word": "عَهْد",
      "root": "ع-ه-د",
      "meanings": [
        "Bund/Vertrag",
        "Versprechen/Geluebde",
        "Befehl/Auftrag",
        "Zeitepoche"
      ],
      "exercises": [
        {
          "ref": "2:124",
          "arabic": "قَالَ لَا يَنَالُ عَهْدِي الظَّالِمِينَ",
          "correctMeaning": "Bund/Vertrag",
          "context": "Gottes عَهْد an Ibrahim — ein Bund, der nicht für Ungerechte gilt."
        },
        {
          "ref": "36:60",
          "arabic": "أَلَمْ أَعْهَدْ إِلَيْكُمْ يَا بَنِي آدَمَ",
          "correctMeaning": "Befehl/Auftrag",
          "context": "أَعْهَدْ إِلَيْكُمْ (habe ich euch nicht aufgetragen?) — Befehl."
        },
        {
          "ref": "2:40",
          "arabic": "وَأَوْفُوا بِعَهْدِي أُوفِ بِعَهْدِكُمْ",
          "correctMeaning": "Versprechen/Geluebde",
          "context": "Gegenseitigkeit (أَوْفُوا/أُوفِ) — beiderseitige Verpflichtung."
        },
        {
          "ref": "19:87",
          "arabic": "لَّا يَمْلِكُونَ الشَّفَاعَةَ إِلَّا مَنِ اتَّخَذَ عِندَ الرَّحْمَٰنِ عَهْدًا",
          "correctMeaning": "Zusage/Versprechen",
          "context": "اتَّخَذَ عَهْدًا (ein Versprechen erlangen) — eine Zusage beim Barmherzigen."
        }
      ]
    },
    {
      "id": 39,
      "word": "أَجَل",
      "root": "ا-ج-ل",
      "meanings": [
        "Frist/Termin",
        "Tod/Lebensende",
        "festgelegter Zeitpunkt"
      ],
      "exercises": [
        {
          "ref": "6:2",
          "arabic": "ثُمَّ قَضَىٰ أَجَلًا وَأَجَلٌ مُّسَمًّى عِندَهُ",
          "correctMeaning": "Frist/Termin",
          "context": "Zwei verschiedene آجال — eine allgemeine Frist und eine benannte (مُّسَمًّى) bei Ihm."
        },
        {
          "ref": "7:34",
          "arabic": "وَلِكُلِّ أُمَّةٍ أَجَلٌ فَإِذَا جَاءَ أَجَلُهُمْ",
          "correctMeaning": "festgelegter Zeitpunkt (des Untergangs)",
          "context": "لِكُلِّ أُمَّةٍ (für jedes Volk) — der vorbestimmte Zeitpunkt ihres Endes."
        },
        {
          "ref": "63:10",
          "arabic": "وَأَنفِقُوا مِن مَّا رَزَقْنَاكُم مِّن قَبْلِ أَن يَأْتِيَ أَحَدَكُمُ الْمَوْتُ",
          "correctMeaning": "Tod/Lebensende",
          "context": "مِّن قَبْلِ أَن يَأْتِيَ الْمَوْتُ — bevor der Tod (als Fristende) kommt."
        },
        {
          "ref": "2:282",
          "arabic": "إِذَا تَدَايَنتُم بِدَيْنٍ إِلَىٰ أَجَلٍ مُّسَمًّى",
          "correctMeaning": "Frist/Zahlungstermin",
          "context": "Im Schuldrecht — إِلَىٰ أَجَلٍ مُّسَمًّى bezeichnet eine festgelegte Zahlungsfrist."
        }
      ]
    },
    {
      "id": 40,
      "word": "بَرَكَة",
      "root": "ب-ر-ك",
      "meanings": [
        "Segen/Segensfuelle",
        "Vermehrung/Wachstum",
        "Bestand/Dauerhaftigkeit"
      ],
      "exercises": [
        {
          "ref": "7:96",
          "arabic": "لَفَتَحْنَا عَلَيْهِم بَرَكَاتٍ مِّنَ السَّمَاءِ وَالْأَرْضِ",
          "correctMeaning": "Segensfuelle/Vermehrung",
          "context": "مِّنَ السَّمَاءِ وَالْأَرْضِ — Segnungen von Himmel und Erde, d.h. reichliche Versorgung."
        },
        {
          "ref": "11:48",
          "arabic": "اهْبِطْ بِسَلَامٍ مِّنَّا وَبَرَكَاتٍ عَلَيْكَ",
          "correctMeaning": "Segen",
          "context": "بِسَلَامٍ وَبَرَكَاتٍ — Segen im Kontext einer Ansprache; parallel zu سَلَام."
        },
        {
          "ref": "11:73",
          "arabic": "رَحْمَتُ اللَّهِ وَبَرَكَاتُهُ عَلَيْكُمْ أَهْلَ الْبَيْتِ",
          "correctMeaning": "Segen/Gnadenerweis",
          "context": "Zusammen mit رَحْمَة genannt — Gottes Segen über die Hausleute."
        }
      ]
    },
    {
      "id": 41,
      "word": "حِسَاب",
      "root": "ح-س-ب",
      "meanings": [
        "Abrechnung/Rechenschaft",
        "Genüge/Ausreichendes",
        "Menge/Zahl"
      ],
      "exercises": [
        {
          "ref": "2:202",
          "arabic": "أُولَٰئِكَ لَهُمْ نَصِيبٌ مِّمَّا كَسَبُوا وَاللَّهُ سَرِيعُ الْحِسَابِ",
          "correctMeaning": "Abrechnung/Rechenschaft",
          "context": "سَرِيعُ الْحِسَابِ — Gott ist schnell in der Abrechnung."
        },
        {
          "ref": "3:27",
          "arabic": "وَتَرْزُقُ مَن تَشَاءُ بِغَيْرِ حِسَابٍ",
          "correctMeaning": "ohne Mass/ohne Begrenzung",
          "context": "بِغَيْرِ حِسَابٍ — ohne Begrenzung, d.h. unbegrenzt/unermesslich."
        },
        {
          "ref": "38:16",
          "arabic": "رَبَّنَا عَجِّل لَّنَا قِطَّنَا قَبْلَ يَوْمِ الْحِسَابِ",
          "correctMeaning": "Abrechnung (Tag der)",
          "context": "يَوْم الْحِسَابِ — der Tag der Abrechnung, eschatologischer Kontext."
        },
        {
          "ref": "65:8",
          "arabic": "فَحَاسَبْنَاهَا حِسَابًا شَدِيدًا",
          "correctMeaning": "Abrechnung (strenge)",
          "context": "حِسَابًا شَدِيدًا (strenge Abrechnung) — Maf'ul mutlaq betont die Härte."
        }
      ]
    },
    {
      "id": 42,
      "word": "مَوْلَى",
      "root": "و-ل-ي",
      "meanings": [
        "Schutzherr/Beschuetzer",
        "Herr/Gebieter",
        "Verbuendeter/Helfer"
      ],
      "exercises": [
        {
          "ref": "2:286",
          "arabic": "أَنتَ مَوْلَانَا فَانصُرْنَا عَلَى الْقَوْمِ الْكَافِرِينَ",
          "correctMeaning": "Schutzherr/Beschuetzer",
          "context": "فَانصُرْنَا (hilf uns) — Gott als Schutzherr, an den man sich um Hilfe wendet."
        },
        {
          "ref": "47:11",
          "arabic": "ذَٰلِكَ بِأَنَّ اللَّهَ مَوْلَى الَّذِينَ آمَنُوا وَأَنَّ الْكَافِرِينَ لَا مَوْلَىٰ لَهُمْ",
          "correctMeaning": "Beschuetzer/Beistand",
          "context": "Gegensatz: Gläubige haben einen مَوْلَى, Nichtglaeubige keinen — Schutz und Beistand."
        },
        {
          "ref": "22:78",
          "arabic": "وَاعْتَصِمُوا بِاللَّهِ هُوَ مَوْلَاكُمْ فَنِعْمَ الْمَوْلَىٰ وَنِعْمَ النَّصِيرُ",
          "correctMeaning": "Schutzherr",
          "context": "Parallel zu نَصِير (Helfer) — مَوْلَى als Schutzherr, der beste seiner Art."
        },
        {
          "ref": "57:15",
          "arabic": "فَالْيَوْمَ لَا يُؤْخَذُ مِنكُمْ فِدْيَةٌ وَلَا مِنَ الَّذِينَ كَفَرُوا مَأْوَاكُمُ النَّارُ هِيَ مَوْلَاكُمْ",
          "correctMeaning": "passendster Ort/Zugehörigkeit",
          "context": "Das Feuer als ihr مَوْلَى — ironisch: der Ort, dem sie am meisten zugehoerig sind."
        }
      ]
    },
    {
      "id": 43,
      "word": "فَرَضَ",
      "root": "ف-ر-ض",
      "meanings": [
        "auferlegen/vorschreiben",
        "bestimmen/festlegen",
        "ermoeglichen/erlauben"
      ],
      "exercises": [
        {
          "ref": "2:236",
          "arabic": "مَا لَمْ تَمَسُّوهُنَّ أَوْ تَفْرِضُوا لَهُنَّ فَرِيضَةً",
          "correctMeaning": "festlegen/bestimmen",
          "context": "فَرِيضَة hier = festgelegter Brautpreis — Bestimmung einer Summe."
        },
        {
          "ref": "24:1",
          "arabic": "سُورَةٌ أَنزَلْنَاهَا وَفَرَضْنَاهَا",
          "correctMeaning": "auferlegen/vorschreiben",
          "context": "وَفَرَضْنَاهَا — wir haben sie als Pflicht auferlegt."
        },
        {
          "ref": "33:50",
          "arabic": "قَدْ عَلِمْنَا مَا فَرَضْنَا عَلَيْهِمْ فِي أَزْوَاجِهِمْ",
          "correctMeaning": "auferlegen/vorschreiben",
          "context": "فَرَضْنَا عَلَيْهِمْ — was wir ihnen bezueglich ihrer Ehefrauen vorgeschrieben haben."
        },
        {
          "ref": "28:85",
          "arabic": "إِنَّ الَّذِي فَرَضَ عَلَيْكَ الْقُرْآنَ",
          "correctMeaning": "auferlegen/zur Pflicht machen",
          "context": "فَرَضَ عَلَيْكَ الْقُرْآنَ — der dir den Quran zur Pflicht machte."
        }
      ]
    },
    {
      "id": 44,
      "word": "شَيْء",
      "root": "ش-ي-ا",
      "meanings": [
        "Ding/Sache",
        "etwas/irgendetwas",
        "Angelegenheit"
      ],
      "exercises": [
        {
          "ref": "36:82",
          "arabic": "إِنَّمَا أَمْرُهُ إِذَا أَرَادَ شَيْئًا أَن يَقُولَ لَهُ كُن فَيَكُونُ",
          "correctMeaning": "Ding/Sache",
          "context": "شَيْئًا als Objekt des Willens — jegliches Ding, das er will."
        },
        {
          "ref": "2:48",
          "arabic": "وَلَا يُقْبَلُ مِنْهَا شَفَاعَةٌ وَلَا يُؤْخَذُ مِنْهَا عَدْلٌ وَلَا هُمْ يُنصَرُونَ",
          "correctMeaning": "etwas/irgendetwas",
          "context": "Im Kontext von Negation — nichts wird angenommen."
        },
        {
          "ref": "4:32",
          "arabic": "لِّلرِّجَالِ نَصِيبٌ مِّمَّا اكْتَسَبُوا وَلِلنِّسَاءِ نَصِيبٌ مِّمَّا اكْتَسَبْنَ",
          "correctMeaning": "Angelegenheit/Anteil",
          "context": "Im Zusammenhang mit Erworbenem — مَا hier als das, was erworben wurde."
        },
        {
          "ref": "18:23",
          "arabic": "وَلَا تَقُولَنَّ لِشَيْءٍ إِنِّي فَاعِلٌ ذَٰلِكَ غَدًا",
          "correctMeaning": "Sache/Angelegenheit",
          "context": "لِشَيْءٍ — bezueglich irgendeiner Sache/Angelegenheit."
        }
      ]
    },
    {
      "id": 45,
      "word": "رُشْد",
      "root": "ر-ش-د",
      "meanings": [
        "Reife/Mündigkeit",
        "Führung",
        "Vernunft/Besonnenheit"
      ],
      "exercises": [
        {
          "ref": "4:6",
          "arabic": "فَإِنْ آنَسْتُم مِّنْهُمْ رُشْدًا فَادْفَعُوا إِلَيْهِمْ أَمْوَالَهُمْ",
          "correctMeaning": "Reife/Mündigkeit",
          "context": "آنَسْتُم (ihr nehmt wahr) — Prüfung der Reife von Waisen, bevor man ihnen ihr Vermögen gibt."
        },
        {
          "ref": "2:256",
          "arabic": "قَد تَّبَيَّنَ الرُّشْدُ مِنَ الْغَيِّ",
          "correctMeaning": "Führung",
          "context": "Gegensatz zu الْغَيّ (Verirrung) — die Führung hat sich von der Verirrung abgehoben."
        },
        {
          "ref": "18:66",
          "arabic": "هَلْ أَتَّبِعُكَ عَلَىٰ أَن تُعَلِّمَنِ مِمَّا عُلِّمْتَ رُشْدًا",
          "correctMeaning": "rechte Erkenntnis/Vernunft",
          "context": "تُعَلِّمَنِ (du lehrst mich) + رُشْدًا — Wissen, das zur Vernunft führt."
        }
      ]
    },
    {
      "id": 46,
      "word": "صَدَقَة",
      "root": "ص-د-ق",
      "meanings": [
        "freiwilliges Almosen",
        "Pflichtabgabe",
        "Brautgabe/Morgengabe"
      ],
      "exercises": [
        {
          "ref": "9:60",
          "arabic": "إِنَّمَا الصَّدَقَاتُ لِلْفُقَرَاءِ وَالْمَسَاكِينِ",
          "correctMeaning": "Pflichtabgabe",
          "context": "إِنَّمَا (ausschließlich) + Aufzählung der acht Kategorien — dies ist eine gesetzliche Regelung."
        },
        {
          "ref": "9:104",
          "arabic": "أَلَمْ يَعْلَمُوا أَنَّ اللَّهَ هُوَ يَقْبَلُ التَّوْبَةَ عَنْ عِبَادِهِ وَيَأْخُذُ الصَّدَقَاتِ",
          "correctMeaning": "Almosen/Spende",
          "context": "يَأْخُذُ (er nimmt an) — freiwillige Gaben, die Gott annimmt."
        },
        {
          "ref": "4:4",
          "arabic": "وَآتُوا النِّسَاءَ صَدُقَاتِهِنَّ نِحْلَةً",
          "correctMeaning": "Brautgabe/Morgengabe",
          "context": "صَدُقَات hier mit anderem Muster — Plural von صَدَاق/صَدُقَة (Brautgabe). نِحْلَةً = als Geschenk."
        }
      ]
    },
    {
      "id": 47,
      "word": "جَنَّة",
      "root": "ج-ن-ن",
      "meanings": [
        "Garten",
        "Paradies/Jenseits-Garten",
        "Verbergung/Abschirmung"
      ],
      "exercises": [
        {
          "ref": "2:265",
          "arabic": "وَمَثَلُ الَّذِينَ يُنفِقُونَ أَمْوَالَهُمُ ابْتِغَاءَ مَرْضَاتِ اللَّهِ كَمَثَلِ جَنَّةٍ بِرَبْوَةٍ",
          "correctMeaning": "Garten (irdisch)",
          "context": "كَمَثَلِ (wie das Gleichnis) + بِرَبْوَةٍ (auf einer Anhoehe) — irdischer Garten im Gleichnis."
        },
        {
          "ref": "2:35",
          "arabic": "وَقُلْنَا يَا آدَمُ اسْكُنْ أَنتَ وَزَوْجُكَ الْجَنَّةَ",
          "correctMeaning": "Paradies/Jenseits-Garten",
          "context": "Anrede an Adam — der Garten, in dem er wohnen sollte."
        },
        {
          "ref": "18:32",
          "arabic": "وَاضْرِبْ لَهُم مَّثَلًا رَّجُلَيْنِ جَعَلْنَا لِأَحَدِهِمَا جَنَّتَيْنِ مِنْ أَعْنَابٍ",
          "correctMeaning": "Garten (irdisch)",
          "context": "جَنَّتَيْنِ مِنْ أَعْنَابٍ (zwei Gärten aus Trauben) — landwirtschaftliche Gärten."
        },
        {
          "ref": "55:46",
          "arabic": "وَلِمَنْ خَافَ مَقَامَ رَبِّهِ جَنَّتَانِ",
          "correctMeaning": "Paradies (eschatologisch)",
          "context": "مَقَام رَبِّهِ — zwei Gärten für den, der das Stehen vor Gott fürchtet."
        }
      ]
    },
    {
      "id": 48,
      "word": "مَعْرُوف",
      "root": "ع-ر-ف",
      "meanings": [
        "Gutes/Rechtes",
        "Angemessenes/Uebliches",
        "Bekanntes/Anerkanntes"
      ],
      "exercises": [
        {
          "ref": "2:228",
          "arabic": "وَلَهُنَّ مِثْلُ الَّذِي عَلَيْهِنَّ بِالْمَعْرُوفِ",
          "correctMeaning": "Angemessenes/Uebliches",
          "context": "بِالْمَعْرُوفِ — in angemessener/ueblicher Weise, im Kontext ehelicher Rechte."
        },
        {
          "ref": "3:104",
          "arabic": "وَلْتَكُن مِّنكُمْ أُمَّةٌ يَدْعُونَ إِلَى الْخَيْرِ وَيَأْمُرُونَ بِالْمَعْرُوفِ",
          "correctMeaning": "Gutes/Rechtes",
          "context": "Gegensatz zu الْمُنكَر — das allgemein Gute/Rechte gebieten."
        },
        {
          "ref": "2:263",
          "arabic": "قَوْلٌ مَّعْرُوفٌ وَمَغْفِرَةٌ خَيْرٌ مِّن صَدَقَةٍ يَتْبَعُهَا أَذًى",
          "correctMeaning": "guetiges/freundliches Wort",
          "context": "قَوْلٌ مَّعْرُوفٌ — ein freundliches Wort ist besser als ein Almosen mit Kraenkung."
        },
        {
          "ref": "4:5",
          "arabic": "وَارْزُقُوهُمْ فِيهَا وَاكْسُوهُمْ وَقُولُوا لَهُمْ قَوْلًا مَّعْرُوفًا",
          "correctMeaning": "angemessen/freundlich",
          "context": "قَوْلًا مَّعْرُوفًا — angemessene Worte zu den Schutzbefohlenen."
        }
      ]
    },
    {
      "id": 49,
      "word": "مُنْكَر",
      "root": "ن-ك-ر",
      "meanings": [
        "Verwerfliches/Unrechtes",
        "Unbekanntes/Fremdes",
        "Abgelehntes"
      ],
      "exercises": [
        {
          "ref": "3:110",
          "arabic": "كُنتُمْ خَيْرَ أُمَّةٍ أُخْرِجَتْ لِلنَّاسِ تَأْمُرُونَ بِالْمَعْرُوفِ وَتَنْهَوْنَ عَنِ الْمُنكَرِ",
          "correctMeaning": "Verwerfliches/Unrechtes",
          "context": "Gegensatz zu الْمَعْرُوف — das Verwerfliche verbieten."
        },
        {
          "ref": "12:70",
          "arabic": "قَالُوا وَأَقْبَلُوا عَلَيْهِمْ مَّاذَا تَفْقِدُونَ",
          "correctMeaning": "Unbekanntes/Unerkanntes",
          "context": "Im Kontext der Yusuf-Geschichte — das Unbekannte/Nicht-Erkannte."
        },
        {
          "ref": "58:2",
          "arabic": "وَإِنَّهُمْ لَيَقُولُونَ مُنكَرًا مِّنَ الْقَوْلِ وَزُورًا",
          "correctMeaning": "Verwerfliches",
          "context": "مُنكَرًا مِّنَ الْقَوْلِ وَزُورًا (Verwerfliches an Rede und Falsches) — sprachlich verwerflich."
        }
      ]
    },
    {
      "id": 50,
      "word": "حَسَنَة",
      "root": "ح-س-ن",
      "meanings": [
        "gute Tat",
        "Wohltat/Wohlergehen",
        "Sieg/Erfolg"
      ],
      "exercises": [
        {
          "ref": "2:201",
          "arabic": "رَبَّنَا آتِنَا فِي الدُّنْيَا حَسَنَةً وَفِي الْآخِرَةِ حَسَنَةً",
          "correctMeaning": "Wohltat/Wohlergehen",
          "context": "In Dunya und Akhira — umfassendes Wohlergehen erbeten."
        },
        {
          "ref": "4:78",
          "arabic": "وَإِن تُصِبْهُمْ حَسَنَةٌ يَقُولُوا هَٰذِهِ مِنْ عِندِ اللَّهِ وَإِن تُصِبْهُمْ سَيِّئَةٌ",
          "correctMeaning": "Glück/Erfolg",
          "context": "Gegensatz zu سَيِّئَة — wenn ihnen Glück widerfahert vs. Unglück."
        },
        {
          "ref": "27:89",
          "arabic": "مَن جَاءَ بِالْحَسَنَةِ فَلَهُ خَيْرٌ مِّنْهَا",
          "correctMeaning": "gute Tat",
          "context": "جَاءَ بِـ (kommen mit) — wer eine gute Tat mitbringt, bekommt Besseres."
        },
        {
          "ref": "3:120",
          "arabic": "إِن تَمْسَسْكُمْ حَسَنَةٌ تَسُؤْهُمْ",
          "correctMeaning": "Erfolg/Sieg",
          "context": "تَسُؤْهُمْ (es missfaellt ihnen) — militaerischer Kontext, Erfolg der Gläubigen."
        }
      ]
    },
    {
      "id": 51,
      "word": "ظُلْم",
      "root": "ظ-ل-م",
      "meanings": [
        "Unrecht/Ungerechtigkeit",
        "Falschplatzierung",
        "Beigesellung (ظُلْم عَظِيم)"
      ],
      "exercises": [
        {
          "ref": "31:13",
          "arabic": "إِنَّ الشِّرْكَ لَظُلْمٌ عَظِيمٌ",
          "correctMeaning": "Beigesellung als Unrecht",
          "context": "الشِّرْك wird explizit als ظُلْم عَظِيم identifiziert — die größte Falschplatzierung."
        },
        {
          "ref": "2:281",
          "arabic": "وَهُمْ لَا يُظْلَمُونَ",
          "correctMeaning": "Unrecht erleiden",
          "context": "لَا يُظْلَمُونَ (ihnen wird nicht Unrecht getan) — jeder bekommt genau, was er verdient."
        },
        {
          "ref": "18:33",
          "arabic": "كِلْتَا الْجَنَّتَيْنِ آتَتْ أُكُلَهَا وَلَمْ تَظْلِم مِّنْهُ شَيْئًا",
          "correctMeaning": "schmaelern/verkürzen",
          "context": "Die Gärten trugen vollen Ertrag — لَمْ تَظْلِم = sie schmaelerten nichts davon."
        },
        {
          "ref": "4:40",
          "arabic": "إِنَّ اللَّهَ لَا يَظْلِمُ مِثْقَالَ ذَرَّةٍ",
          "correctMeaning": "Unrecht tun/verkürzen",
          "context": "مِثْقَالَ ذَرَّةٍ (auch nicht das Gewicht eines Stäubchens) — nicht das Geringste wird verkürzt."
        }
      ]
    },
    {
      "id": 52,
      "word": "كُرْسِيّ",
      "root": "ك-ر-س",
      "meanings": [
        "Thron/Sitz",
        "Herrschaftsbereich",
        "Wissen/Macht"
      ],
      "exercises": [
        {
          "ref": "2:255",
          "arabic": "وَسِعَ كُرْسِيُّهُ السَّمَاوَاتِ وَالْأَرْضَ",
          "correctMeaning": "Herrschaftsbereich/Thron",
          "context": "وَسِعَ (umfasst) + السَّمَاوَاتِ وَالْأَرْضَ — sein Kursiy umfasst Himmel und Erde."
        },
        {
          "ref": "38:34",
          "arabic": "وَلَقَدْ فَتَنَّا سُلَيْمَانَ وَأَلْقَيْنَا عَلَىٰ كُرْسِيِّهِ جَسَدًا",
          "correctMeaning": "Thron/Sitz (wörtlich)",
          "context": "عَلَىٰ كُرْسِيِّهِ (auf seinen Thron) — ein Körper wurde auf Sulaimans Thron geworfen."
        },
        {
          "ref": "2:255",
          "arabic": "اللَّهُ لَا إِلَٰهَ إِلَّا هُوَ الْحَيُّ الْقَيُّومُ",
          "correctMeaning": "Herrschaft/Autorität",
          "context": "Im Gesamtkontext von 2:255 — die Attribute الْحَيّ الْقَيُّوم deuten auf umfassende Herrschaft."
        }
      ]
    },
    {
      "id": 53,
      "word": "بَيْت",
      "root": "ب-ي-ت",
      "meanings": [
        "Haus/Wohnung",
        "Tempel/Gebetsstätte",
        "Familie/Haushalt"
      ],
      "exercises": [
        {
          "ref": "2:125",
          "arabic": "وَإِذْ جَعَلْنَا الْبَيْتَ مَثَابَةً لِّلنَّاسِ وَأَمْنًا",
          "correctMeaning": "Tempel/Gebetsstätte (Kaaba)",
          "context": "مَثَابَةً لِّلنَّاسِ (Zufluchtsort für die Menschen) — das Haus Gottes in Mekka."
        },
        {
          "ref": "33:33",
          "arabic": "وَقَرْنَ فِي بُيُوتِكُنَّ",
          "correctMeaning": "Haus/Wohnung",
          "context": "بُيُوتِكُنَّ (eure Häuser) mit Possessivsuffix — wörtliche Wohnhaeuser."
        },
        {
          "ref": "33:33",
          "arabic": "إِنَّمَا يُرِيدُ اللَّهُ لِيُذْهِبَ عَنكُمُ الرِّجْسَ أَهْلَ الْبَيْتِ",
          "correctMeaning": "Familie/Haushalt",
          "context": "أَهْلَ الْبَيْتِ (Leute des Hauses) — Bezeichnung für die Familie."
        },
        {
          "ref": "2:189",
          "arabic": "وَلَيْسَ الْبِرُّ بِأَن تَأْتُوا الْبُيُوتَ مِن ظُهُورِهَا",
          "correctMeaning": "Haus (wörtlich)",
          "context": "مِن ظُهُورِهَا (von ihren Rückseiten) — physische Häuser mit Eingaengen."
        }
      ]
    },
    {
      "id": 54,
      "word": "قَرْيَة",
      "root": "ق-ر-ي",
      "meanings": [
        "Dorf/Ortschaft",
        "Stadt",
        "Bewohner (metonymisch)"
      ],
      "exercises": [
        {
          "ref": "2:259",
          "arabic": "أَوْ كَالَّذِي مَرَّ عَلَىٰ قَرْيَةٍ وَهِيَ خَاوِيَةٌ عَلَىٰ عُرُوشِهَا",
          "correctMeaning": "Ortschaft/Stadt",
          "context": "خَاوِيَةٌ عَلَىٰ عُرُوشِهَا (auf ihren Daechern zusammengefallen) — physische Ortschaft."
        },
        {
          "ref": "4:75",
          "arabic": "رَبَّنَا أَخْرِجْنَا مِنْ هَٰذِهِ الْقَرْيَةِ الظَّالِمِ أَهْلُهَا",
          "correctMeaning": "Stadt (mit Bewohnern)",
          "context": "الظَّالِمِ أَهْلُهَا — die Stadt, deren Bewohner ungerecht sind. قَرْيَة steht für den Ort."
        },
        {
          "ref": "21:11",
          "arabic": "وَكَمْ قَصَمْنَا مِن قَرْيَةٍ كَانَتْ ظَالِمَةً",
          "correctMeaning": "Bewohner (metonymisch)",
          "context": "كَانَتْ ظَالِمَةً (sie war ungerecht) — die قَرْيَة selbst kann nicht ungerecht sein, gemeint sind die Bewohner."
        },
        {
          "ref": "12:82",
          "arabic": "وَاسْأَلِ الْقَرْيَةَ الَّتِي كُنَّا فِيهَا",
          "correctMeaning": "Bewohner (metonymisch)",
          "context": "وَاسْأَلِ (frag!) — man fragt nicht eine Ortschaft, sondern ihre Bewohner. Metonymie."
        }
      ]
    },
    {
      "id": 55,
      "word": "مِلَّة",
      "root": "م-ل-ل",
      "meanings": [
        "Glaubensgemeinschaft/Religion",
        "Weg/Lebensweise",
        "Bekenntnis"
      ],
      "exercises": [
        {
          "ref": "2:130",
          "arabic": "وَمَن يَرْغَبُ عَن مِّلَّةِ إِبْرَاهِيمَ إِلَّا مَن سَفِهَ نَفْسَهُ",
          "correctMeaning": "Religion/Glaubensweise",
          "context": "مِّلَّةِ إِبْرَاهِيمَ — die Religion/Glaubensweise Ibrahims als Gegenstand."
        },
        {
          "ref": "12:37",
          "arabic": "إِنِّي تَرَكْتُ مِلَّةَ قَوْمٍ لَّا يُؤْمِنُونَ بِاللَّهِ",
          "correctMeaning": "Glaubensrichtung/Lebensweise",
          "context": "تَرَكْتُ (ich habe verlassen) — Yusuf verliess die Lebensweise eines unglaeubigen Volkes."
        },
        {
          "ref": "38:7",
          "arabic": "مَا سَمِعْنَا بِهَٰذَا فِي الْمِلَّةِ الْآخِرَةِ",
          "correctMeaning": "Religion/Bekenntnis",
          "context": "الْمِلَّةِ الْآخِرَةِ (die letzte/juengste Religion) — Vergleich mit frueherem Bekenntnis."
        }
      ]
    },
    {
      "id": 56,
      "word": "أَسْمَاء",
      "root": "س-م-و",
      "meanings": [
        "Namen",
        "Attribute/Bezeichnungen",
        "blosse Benennungen (ohne Realität)"
      ],
      "exercises": [
        {
          "ref": "2:31",
          "arabic": "وَعَلَّمَ آدَمَ الْأَسْمَاءَ كُلَّهَا",
          "correctMeaning": "Namen/Bezeichnungen",
          "context": "عَلَّمَ (er lehrte) + كُلَّهَا (alle) — Gott lehrte Adam saemtliche Namen."
        },
        {
          "ref": "7:180",
          "arabic": "وَلِلَّهِ الْأَسْمَاءُ الْحُسْنَىٰ فَادْعُوهُ بِهَا",
          "correctMeaning": "Attribute/Namen (Gottes)",
          "context": "الْحُسْنَىٰ (die schönsten) — Gottes schöne Namen/Attribute."
        },
        {
          "ref": "12:40",
          "arabic": "مَا تَعْبُدُونَ مِن دُونِهِ إِلَّا أَسْمَاءً سَمَّيْتُمُوهَا",
          "correctMeaning": "blosse Benennungen (ohne Realität)",
          "context": "سَمَّيْتُمُوهَا (die ihr benannt habt) — der Text bestreitet die Realität hinter diesen Benennungen."
        },
        {
          "ref": "53:23",
          "arabic": "إِنْ هِيَ إِلَّا أَسْمَاءٌ سَمَّيْتُمُوهَا أَنتُمْ وَآبَاؤُكُم",
          "correctMeaning": "blosse Benennungen (ohne Substanz)",
          "context": "Gleiche Struktur — die Götzen sind nur selbsterfundene Namen."
        }
      ]
    },
    {
      "id": 57,
      "word": "ضَلَال",
      "root": "ض-ل-ل",
      "meanings": [
        "Abirren/Verirrung",
        "Verlust/Verlorenheit",
        "Vergessenheit/Verschwinden"
      ],
      "exercises": [
        {
          "ref": "1:7",
          "arabic": "غَيْرِ الْمَغْضُوبِ عَلَيْهِمْ وَلَا الضَّالِّينَ",
          "correctMeaning": "Abirren/Verirrung",
          "context": "الضَّالِّين als Gegensatz zur Führung (الصِّرَاطَ الْمُسْتَقِيمَ) — die Verirrten."
        },
        {
          "ref": "12:8",
          "arabic": "إِنَّ أَبَانَا لَفِي ضَلَالٍ مُّبِينٍ",
          "correctMeaning": "Irrtum/Fehleinschaetzung",
          "context": "Die Brüder Yusufs über ihren Vater — er sei in offensichtlichem Irrtum."
        },
        {
          "ref": "93:7",
          "arabic": "وَوَجَدَكَ ضَالًّا فَهَدَىٰ",
          "correctMeaning": "suchend/ohne Orientierung",
          "context": "ضَالًّا im Kontrast zu فَهَدَىٰ (und er leitete dich) — Zustand vor der Führung."
        },
        {
          "ref": "26:20",
          "arabic": "قَالَ فَعَلْتُهَا إِذًا وَأَنَا مِنَ الضَّالِّينَ",
          "correctMeaning": "Unwissenheit/Unbeabsichtigtheit",
          "context": "Musa über seine Tat — er handelte in Unwissenheit, nicht mit Absicht."
        }
      ]
    },
    {
      "id": 58,
      "word": "مَقَام",
      "root": "ق-و-م",
      "meanings": [
        "Ort/Standort",
        "Rang/Stellung",
        "Aufenthalt/Wohnstätte"
      ],
      "exercises": [
        {
          "ref": "2:125",
          "arabic": "وَاتَّخِذُوا مِن مَّقَامِ إِبْرَاهِيمَ مُصَلًّى",
          "correctMeaning": "Standort (Ibrahims)",
          "context": "مَّقَامِ إِبْرَاهِيمَ — der physische Ort, wo Ibrahim stand."
        },
        {
          "ref": "17:79",
          "arabic": "عَسَىٰ أَن يَبْعَثَكَ رَبُّكَ مَقَامًا مَحْمُودًا",
          "correctMeaning": "Rang/Stellung",
          "context": "مَحْمُودًا (gelobt) — eine gelobte Stellung/ein hoher Rang."
        },
        {
          "ref": "55:46",
          "arabic": "وَلِمَنْ خَافَ مَقَامَ رَبِّهِ جَنَّتَانِ",
          "correctMeaning": "Stehen vor (dem Herrn)",
          "context": "مَقَام رَبِّهِ — das Stehen vor dem Herrn am Tag der Abrechnung."
        },
        {
          "ref": "44:26",
          "arabic": "وَزُرُوعٍ وَمَقَامٍ كَرِيمٍ",
          "correctMeaning": "Aufenthaltsort/Wohnstätte",
          "context": "مَقَامٍ كَرِيمٍ (edler Aufenthalt) — die praechtige Wohnstätte, die sie zurückliessen."
        }
      ]
    },
    {
      "id": 59,
      "word": "بَاطِل",
      "root": "ب-ط-ل",
      "meanings": [
        "Falschheit/Lüge",
        "Nichtiges/Wertloses",
        "Vergängliches"
      ],
      "exercises": [
        {
          "ref": "2:42",
          "arabic": "وَلَا تَلْبِسُوا الْحَقَّ بِالْبَاطِلِ",
          "correctMeaning": "Falschheit/Lüge",
          "context": "Gegensatz zu الْحَقّ — die Wahrheit nicht mit Falschheit vermischen."
        },
        {
          "ref": "3:191",
          "arabic": "رَبَّنَا مَا خَلَقْتَ هَٰذَا بَاطِلًا",
          "correctMeaning": "zwecklos/nichtig",
          "context": "مَا خَلَقْتَ بَاطِلًا — du hast dies nicht zwecklos erschaffen."
        },
        {
          "ref": "17:81",
          "arabic": "وَقُلْ جَاءَ الْحَقُّ وَزَهَقَ الْبَاطِلُ إِنَّ الْبَاطِلَ كَانَ زَهُوقًا",
          "correctMeaning": "das Vergängliche/Nichtige",
          "context": "زَهَقَ (vergehen/verschwinden) + زَهُوقًا — das Nichtige ist seiner Natur nach vergänglich."
        },
        {
          "ref": "4:29",
          "arabic": "لَا تَأْكُلُوا أَمْوَالَكُم بَيْنَكُم بِالْبَاطِلِ",
          "correctMeaning": "auf unrechtmaessige Weise",
          "context": "بِالْبَاطِلِ — als Adverbial: auf nichtige/unrechtmaessige Weise Vermögen verzehren."
        }
      ]
    },
    {
      "id": 60,
      "word": "تَقْوَى",
      "root": "و-ق-ي",
      "meanings": [
        "Achtsamkeit/Vorsicht",
        "Schutz/Bewahrung",
        "Pflichtbewusstsein"
      ],
      "exercises": [
        {
          "ref": "2:197",
          "arabic": "وَتَزَوَّدُوا فَإِنَّ خَيْرَ الزَّادِ التَّقْوَىٰ",
          "correctMeaning": "Achtsamkeit/Vorsicht",
          "context": "خَيْرَ الزَّادِ (beste Wegzehrung) — Taqwa als beste Vorbereitung."
        },
        {
          "ref": "49:13",
          "arabic": "إِنَّ أَكْرَمَكُمْ عِندَ اللَّهِ أَتْقَاكُمْ",
          "correctMeaning": "Pflichtbewusstsein",
          "context": "أَكْرَمَكُمْ (der Edelste von euch) — der Massstab ist die Taqwa."
        },
        {
          "ref": "5:2",
          "arabic": "وَتَعَاوَنُوا عَلَى الْبِرِّ وَالتَّقْوَىٰ",
          "correctMeaning": "Pflichtbewusstsein",
          "context": "Parallel zu الْبِرّ (Güte) — Zusammenarbeit in Güte und pflichtbewusster Achtsamkeit."
        },
        {
          "ref": "91:8",
          "arabic": "فَأَلْهَمَهَا فُجُورَهَا وَتَقْوَاهَا",
          "correctMeaning": "Schutz/Bewahrung (vor Sünde)",
          "context": "Gegensatz zu فُجُور (Frevel) — die Fähigkeit, sich vor Sünde zu schützen."
        }
      ]
    },
    {
      "id": 61,
      "word": "سَيِّئَة",
      "root": "س-و-ا",
      "meanings": [
        "schlechte Tat/Sünde",
        "Unglück/Widerwärtigkeit",
        "Strafe/Vergeltung"
      ],
      "exercises": [
        {
          "ref": "42:25",
          "arabic": "وَيَعْفُو عَنِ السَّيِّئَاتِ",
          "correctMeaning": "schlechte Taten/Sünden",
          "context": "يَعْفُو عَن (er vergibt) — Vergebung von Sünden."
        },
        {
          "ref": "4:78",
          "arabic": "وَإِن تُصِبْهُمْ سَيِّئَةٌ يَقُولُوا هَٰذِهِ مِنْ عِندِكَ",
          "correctMeaning": "Unglück/Widerwärtigkeit",
          "context": "تُصِبْهُمْ (trifft sie) — Gegensatz zu حَسَنَة, etwas das einen trifft: Unglück."
        },
        {
          "ref": "13:6",
          "arabic": "وَيَسْتَعْجِلُونَكَ بِالسَّيِّئَةِ قَبْلَ الْحَسَنَةِ",
          "correctMeaning": "Strafe/Vergeltung",
          "context": "يَسْتَعْجِلُونَ (sie draengen auf Beschleunigung) — sie fordern die Strafe heraus."
        },
        {
          "ref": "17:7",
          "arabic": "وَإِنْ أَسَأْتُمْ فَلَهَا",
          "correctMeaning": "Böses/Schlechtes tun",
          "context": "Verb أَسَاءَ — wenn ihr schlecht handelt, ist es zu eurem Nachteil."
        }
      ]
    },
    {
      "id": 62,
      "word": "فَاحِشَة",
      "root": "ف-ح-ش",
      "meanings": [
        "Unsittlichkeit/Obszoenität",
        "Ehebruch/Unzucht",
        "Übermass/Ungeheuerlichkeit"
      ],
      "exercises": [
        {
          "ref": "4:15",
          "arabic": "وَاللَّاتِي يَأْتِينَ الْفَاحِشَةَ مِن نِّسَائِكُمْ",
          "correctMeaning": "Unzucht/Unsittlichkeit",
          "context": "يَأْتِينَ الْفَاحِشَةَ (die Fahisha begehen) — sexuelles Fehlverhalten."
        },
        {
          "ref": "7:80",
          "arabic": "أَتَأْتُونَ الْفَاحِشَةَ مَا سَبَقَكُم بِهَا مِنْ أَحَدٍ",
          "correctMeaning": "Unsittlichkeit/Obszoenität",
          "context": "Luts Volk — مَا سَبَقَكُم (niemand hat euch darin vorangetan): eine beispiellose Obszoenität."
        },
        {
          "ref": "2:169",
          "arabic": "إِنَّمَا يَأْمُرُكُم بِالسُّوءِ وَالْفَحْشَاءِ",
          "correctMeaning": "das Abscheuliche/Ungeheure",
          "context": "Parallel zu السُّوء (das Ueble) — Schaitan befiehlt das Abscheuliche."
        },
        {
          "ref": "65:1",
          "arabic": "لَا تُخْرِجُوهُنَّ مِن بُيُوتِهِنَّ وَلَا يَخْرُجْنَ إِلَّا أَن يَأْتِينَ بِفَاحِشَةٍ مُّبَيِّنَةٍ",
          "correctMeaning": "klare Unsittlichkeit",
          "context": "بِفَاحِشَةٍ مُّبَيِّنَةٍ (mit offenkundiger Fahisha) — im Kontext der Scheidungswartezeit."
        }
      ]
    },
    {
      "id": 63,
      "word": "إِمَام",
      "root": "ا-م-م",
      "meanings": [
        "Anführer/Leiter",
        "Buch/Verzeichnis",
        "Weg/Straße",
        "Vorbild"
      ],
      "exercises": [
        {
          "ref": "2:124",
          "arabic": "قَالَ إِنِّي جَاعِلُكَ لِلنَّاسِ إِمَامًا",
          "correctMeaning": "Vorbild/Anführer",
          "context": "جَاعِلُكَ (ich mache dich) + لِلنَّاسِ — Ibrahim als Vorbild für die Menschen."
        },
        {
          "ref": "36:12",
          "arabic": "وَكُلَّ شَيْءٍ أَحْصَيْنَاهُ فِي إِمَامٍ مُّبِينٍ",
          "correctMeaning": "Buch/Verzeichnis",
          "context": "أَحْصَيْنَاهُ (wir haben es erfasst) + فِي — alles wurde in einem klaren Verzeichnis festgehalten."
        },
        {
          "ref": "15:79",
          "arabic": "وَإِنَّهُمَا لَبِإِمَامٍ مُّبِينٍ",
          "correctMeaning": "Weg/Straße",
          "context": "لَبِإِمَامٍ مُّبِينٍ — beide (Städte) liegen an einem klaren Weg/einer deutlichen Straße."
        },
        {
          "ref": "25:74",
          "arabic": "وَاجْعَلْنَا لِلْمُتَّقِينَ إِمَامًا",
          "correctMeaning": "Vorbild/Anführer",
          "context": "Bittgebet — mach uns zu Vorbildern für die Gottesbewussten."
        }
      ]
    },
    {
      "id": 64,
      "word": "حِزْب",
      "root": "ح-ز-ب",
      "meanings": [
        "Partei/Gruppe",
        "Anhaengerschaft",
        "Gegnerschaft/feindliche Gruppe"
      ],
      "exercises": [
        {
          "ref": "5:56",
          "arabic": "وَمَن يَتَوَلَّ اللَّهَ وَرَسُولَهُ وَالَّذِينَ آمَنُوا فَإِنَّ حِزْبَ اللَّهِ هُمُ الْغَالِبُونَ",
          "correctMeaning": "Partei/Anhaengerschaft (Gottes)",
          "context": "حِزْبَ اللَّهِ — die Partei Gottes, die die Oberhand behaelt."
        },
        {
          "ref": "58:19",
          "arabic": "اسْتَحْوَذَ عَلَيْهِمُ الشَّيْطَانُ فَأَنسَاهُمْ ذِكْرَ اللَّهِ أُولَٰئِكَ حِزْبُ الشَّيْطَانِ",
          "correctMeaning": "Partei (des Satans)",
          "context": "حِزْبُ الشَّيْطَانِ — die Partei des Teufels als Gegenstück zu حِزْب اللَّهِ."
        },
        {
          "ref": "33:20",
          "arabic": "يَحْسَبُونَ الْأَحْزَابَ لَمْ يَذْهَبُوا",
          "correctMeaning": "feindliche Gruppen/Koalitionen",
          "context": "الْأَحْزَاب (die Koalitionen) — die verbuendeten feindlichen Gruppen (vgl. Sure 33: al-Ahzab)."
        },
        {
          "ref": "23:53",
          "arabic": "فَتَقَطَّعُوا أَمْرَهُم بَيْنَهُمْ زُبُرًا كُلُّ حِزْبٍ بِمَا لَدَيْهِمْ فَرِحُونَ",
          "correctMeaning": "Gruppe/Sekte",
          "context": "كُلُّ حِزْبٍ (jede Gruppe) — jede Gruppe freut sich über das, was sie hat."
        }
      ]
    },
    {
      "id": 65,
      "word": "سُنَّة",
      "root": "س-ن-ن",
      "meanings": [
        "Verfahrensweise/Gesetzmässigkeit",
        "Brauch/Gewohnheit",
        "Gottes Vorgehen (mit frueheren Völkern)"
      ],
      "exercises": [
        {
          "ref": "33:62",
          "arabic": "سُنَّةَ اللَّهِ فِي الَّذِينَ خَلَوْا مِن قَبْلُ وَلَن تَجِدَ لِسُنَّةِ اللَّهِ تَبْدِيلًا",
          "correctMeaning": "Gottes Verfahrensweise",
          "context": "لَن تَجِدَ تَبْدِيلًا (du wirst keine Änderung finden) — Gottes unveränderliche Vorgehensweise."
        },
        {
          "ref": "35:43",
          "arabic": "فَلَن تَجِدَ لِسُنَّتِ اللَّهِ تَبْدِيلًا وَلَن تَجِدَ لِسُنَّتِ اللَّهِ تَحْوِيلًا",
          "correctMeaning": "Gesetzmässigkeit Gottes",
          "context": "تَبْدِيلًا/تَحْوِيلًا — weder Änderung noch Abweichung: feste Gesetzmässigkeit."
        },
        {
          "ref": "8:38",
          "arabic": "قُل لِّلَّذِينَ كَفَرُوا إِن يَنتَهُوا يُغْفَرْ لَهُم مَّا قَدْ سَلَفَ وَإِن يَعُودُوا فَقَدْ مَضَتْ سُنَّتُ الْأَوَّلِينَ",
          "correctMeaning": "Verfahrensweise (mit den Frueheren)",
          "context": "سُنَّتُ الْأَوَّلِينَ — die Vorgehensweise gegenüber den frueheren Völkern ist bereits ergangen."
        },
        {
          "ref": "15:13",
          "arabic": "وَقَدْ خَلَتْ سُنَّةُ الْأَوَّلِينَ",
          "correctMeaning": "Brauch/Verfahren der Frueheren",
          "context": "خَلَتْ (vergangen) — das Beispiel/Verfahren der frueheren Völker ist bereits geschehen."
        }
      ]
    },
    {
      "id": 66,
      "word": "شَأْن",
      "root": "ش-ا-ن",
      "meanings": [
        "Angelegenheit/Sache",
        "Zustand/Lage",
        "Rang/Bedeutung"
      ],
      "exercises": [
        {
          "ref": "10:61",
          "arabic": "وَمَا تَكُونُ فِي شَأْنٍ وَمَا تَتْلُو مِنْهُ مِن قُرْآنٍ",
          "correctMeaning": "Angelegenheit/Beschäftigung",
          "context": "فِي شَأْنٍ — in welcher Angelegenheit du auch bist."
        },
        {
          "ref": "55:29",
          "arabic": "كُلَّ يَوْمٍ هُوَ فِي شَأْنٍ",
          "correctMeaning": "Angelegenheit/Wirken",
          "context": "Jeden Tag ist Er in einer (neuen) Angelegenheit — شَأْن als Ausdruck fortwaehrender Aktivität."
        },
        {
          "ref": "80:37",
          "arabic": "لِكُلِّ امْرِئٍ مِّنْهُمْ يَوْمَئِذٍ شَأْنٌ يُغْنِيهِ",
          "correctMeaning": "Zustand/Angelegenheit (die ihn beschäftigt)",
          "context": "شَأْنٌ يُغْنِيهِ — jeder hat an jenem Tag eine Angelegenheit, die ihn völlig in Anspruch nimmt."
        }
      ]
    },
    {
      "id": 67,
      "word": "رِزْق",
      "root": "ر-ز-ق",
      "meanings": [
        "Versorgung/Lebensunterhalt",
        "Nahrung/Speise",
        "Anteil/Zuteilung"
      ],
      "exercises": [
        {
          "ref": "2:22",
          "arabic": "وَأَنزَلَ مِنَ السَّمَاءِ مَاءً فَأَخْرَجَ بِهِ مِنَ الثَّمَرَاتِ رِزْقًا لَّكُمْ",
          "correctMeaning": "Nahrung/Speise",
          "context": "مِنَ الثَّمَرَات (von den Früchten) — konkrete Nahrung als Versorgung."
        },
        {
          "ref": "17:30",
          "arabic": "إِنَّ رَبَّكَ يَبْسُطُ الرِّزْقَ لِمَن يَشَاءُ وَيَقْدِرُ",
          "correctMeaning": "Versorgung/Lebensunterhalt",
          "context": "يَبْسُطُ/يَقْدِرُ (er weitet/er bemisst) — allgemeiner Lebensunterhalt."
        },
        {
          "ref": "8:4",
          "arabic": "أُولَٰئِكَ هُمُ الْمُؤْمِنُونَ حَقًّا لَّهُمْ دَرَجَاتٌ عِندَ رَبِّهِمْ وَمَغْفِرَةٌ وَرِزْقٌ كَرِيمٌ",
          "correctMeaning": "Zuteilung/Gabe (im Jenseits)",
          "context": "رِزْقٌ كَرِيمٌ (edle Zuteilung) — Gabe im Jenseits."
        },
        {
          "ref": "40:13",
          "arabic": "وَيُنَزِّلُ لَكُم مِّنَ السَّمَاءِ رِزْقًا",
          "correctMeaning": "Regen (als Versorgung)",
          "context": "مِّنَ السَّمَاءِ — Regen als Form von رِزْق (Versorgung) im textuellen Kontext."
        }
      ]
    },
    {
      "id": 68,
      "word": "كَسَبَ",
      "root": "ك-س-ب",
      "meanings": [
        "erwerben/verdienen",
        "begehen (Sünde)",
        "sich zuziehen"
      ],
      "exercises": [
        {
          "ref": "2:134",
          "arabic": "لَهَا مَا كَسَبَتْ وَلَكُم مَّا كَسَبْتُمْ",
          "correctMeaning": "erwerben/verdienen",
          "context": "Jeder trägt, was er erworben hat — allgemeines Erwerben von Taten."
        },
        {
          "ref": "2:81",
          "arabic": "بَلَىٰ مَن كَسَبَ سَيِّئَةً وَأَحَاطَتْ بِهِ خَطِيئَتُهُ",
          "correctMeaning": "begehen (Sünde)",
          "context": "كَسَبَ سَيِّئَةً — eine schlechte Tat begehen; خَطِيئَة umschliesst ihn."
        },
        {
          "ref": "2:286",
          "arabic": "لَهَا مَا كَسَبَتْ وَعَلَيْهَا مَا اكْتَسَبَتْ",
          "correctMeaning": "erwerben (Gutes) vs. sich zuziehen (Schlechtes)",
          "context": "كَسَبَتْ (Stamm I: Gutes erwerben) vs. اكْتَسَبَتْ (Stamm VIII: sich Schlechtes zuziehen) — feiner Unterschied."
        },
        {
          "ref": "45:22",
          "arabic": "وَلِتُجْزَىٰ كُلُّ نَفْسٍ بِمَا كَسَبَتْ",
          "correctMeaning": "erwerben/ansammeln",
          "context": "بِمَا كَسَبَتْ — jede Seele wird nach dem vergolten, was sie erworben hat."
        }
      ]
    },
    {
      "id": 69,
      "word": "ذُرِّيَّة",
      "root": "ذ-ر-ر",
      "meanings": [
        "Nachkommenschaft",
        "Kinder",
        "Vorfahren (umgekehrte Richtung!)"
      ],
      "exercises": [
        {
          "ref": "2:124",
          "arabic": "قَالَ وَمِن ذُرِّيَّتِي قَالَ لَا يَنَالُ عَهْدِي الظَّالِمِينَ",
          "correctMeaning": "Nachkommenschaft",
          "context": "Ibrahim fragt nach seinen Nachkommen — ob der Bund auch für sie gilt."
        },
        {
          "ref": "19:58",
          "arabic": "أُولَٰئِكَ الَّذِينَ أَنْعَمَ اللَّهُ عَلَيْهِم مِّنَ النَّبِيِّينَ مِن ذُرِّيَّةِ آدَمَ",
          "correctMeaning": "Nachkommenschaft (allgemein)",
          "context": "مِن ذُرِّيَّةِ آدَمَ — aus der Nachkommenschaft Adams."
        },
        {
          "ref": "36:41",
          "arabic": "وَآيَةٌ لَّهُمْ أَنَّا حَمَلْنَا ذُرِّيَّتَهُمْ فِي الْفُلْكِ الْمَشْحُونِ",
          "correctMeaning": "Vorfahren",
          "context": "حَمَلْنَا ذُرِّيَّتَهُمْ فِي الْفُلْكِ — im Schiff (Nuhs) wurden ihre Vorfahren getragen, nicht ihre Nachkommen."
        },
        {
          "ref": "7:172",
          "arabic": "وَإِذْ أَخَذَ رَبُّكَ مِن بَنِي آدَمَ مِن ظُهُورِهِمْ ذُرِّيَّتَهُمْ",
          "correctMeaning": "Nachkommen (aus den Rücken)",
          "context": "مِن ظُهُورِهِمْ (aus ihren Rücken) — die Nachkommen wurden aus den Lenden genommen."
        }
      ]
    },
    {
      "id": 70,
      "word": "تَوْبَة",
      "root": "ت-و-ب",
      "meanings": [
        "Reue/Umkehr (des Menschen)",
        "Vergebung/Zuwendung (von Gott)",
        "Rückkehr"
      ],
      "exercises": [
        {
          "ref": "4:17",
          "arabic": "إِنَّمَا التَّوْبَةُ عَلَى اللَّهِ لِلَّذِينَ يَعْمَلُونَ السُّوءَ بِجَهَالَةٍ",
          "correctMeaning": "Vergebung/Zuwendung Gottes",
          "context": "التَّوْبَةُ عَلَى اللَّهِ — hier ist es Gottes Zuwendung/Annahme der Reue, die ihm obliegt."
        },
        {
          "ref": "9:118",
          "arabic": "ثُمَّ تَابَ عَلَيْهِمْ لِيَتُوبُوا",
          "correctMeaning": "Zuwendung Gottes (damit sie umkehren)",
          "context": "تَابَ عَلَيْهِمْ (er wandte sich ihnen zu) — Gott wendet sich ihnen zu, damit sie umkehren."
        },
        {
          "ref": "66:8",
          "arabic": "يَا أَيُّهَا الَّذِينَ آمَنُوا تُوبُوا إِلَى اللَّهِ تَوْبَةً نَّصُوحًا",
          "correctMeaning": "Reue/Umkehr (des Menschen)",
          "context": "تُوبُوا (kehrt um!) + نَّصُوحًا (aufrichtig) — menschliche Reue und Umkehr."
        },
        {
          "ref": "4:18",
          "arabic": "وَلَيْسَتِ التَّوْبَةُ لِلَّذِينَ يَعْمَلُونَ السَّيِّئَاتِ",
          "correctMeaning": "Reue/Möglichkeit zur Umkehr",
          "context": "Negation — die Reue gilt nicht für diejenigen, die bis zum Tod suendigen."
        }
      ]
    },
    {
      "id": 71,
      "word": "فِئَة",
      "root": "ف-ي-ا",
      "meanings": [
        "Gruppe/Truppe",
        "Schar/Partei",
        "Stützgruppe"
      ],
      "exercises": [
        {
          "ref": "2:249",
          "arabic": "كَم مِّن فِئَةٍ قَلِيلَةٍ غَلَبَتْ فِئَةً كَثِيرَةً بِإِذْنِ اللَّهِ",
          "correctMeaning": "Truppe/Kampfgruppe",
          "context": "غَلَبَتْ (besiegte) — militaerischer Kontext: eine kleine Truppe besiegt eine grosse."
        },
        {
          "ref": "3:13",
          "arabic": "قَدْ كَانَ لَكُمْ آيَةٌ فِي فِئَتَيْنِ الْتَقَتَا",
          "correctMeaning": "Gruppe/Heeresgruppe",
          "context": "الْتَقَتَا (die aufeinandertrafen) — zwei Gruppen im Kampf."
        },
        {
          "ref": "28:81",
          "arabic": "فَمَا كَانَ لَهُ مِن فِئَةٍ يَنصُرُونَهُ مِن دُونِ اللَّهِ",
          "correctMeaning": "Stützgruppe/Helfer",
          "context": "يَنصُرُونَهُ (die ihm helfen) — Qarun hatte keine Stützgruppe, die ihm beistand."
        }
      ]
    },
    {
      "id": 72,
      "word": "شِفَاء",
      "root": "ش-ف-ي",
      "meanings": [
        "Heilung (körperlich)",
        "Heilung (seelisch/geistig)",
        "Heilmittel"
      ],
      "exercises": [
        {
          "ref": "10:57",
          "arabic": "يَا أَيُّهَا النَّاسُ قَدْ جَاءَتْكُم مَّوْعِظَةٌ مِّن رَّبِّكُمْ وَشِفَاءٌ لِّمَا فِي الصُّدُورِ",
          "correctMeaning": "Heilung (seelisch)",
          "context": "لِّمَا فِي الصُّدُورِ (für das, was in den Bruesten ist) — Heilung für innere Krankheiten."
        },
        {
          "ref": "16:69",
          "arabic": "يَخْرُجُ مِن بُطُونِهَا شَرَابٌ مُّخْتَلِفٌ أَلْوَانُهُ فِيهِ شِفَاءٌ لِّلنَّاسِ",
          "correctMeaning": "Heilmittel (körperlich)",
          "context": "شَرَابٌ (Getraenk) aus Bienen — Honig als physisches Heilmittel."
        },
        {
          "ref": "17:82",
          "arabic": "وَنُنَزِّلُ مِنَ الْقُرْآنِ مَا هُوَ شِفَاءٌ وَرَحْمَةٌ لِّلْمُؤْمِنِينَ",
          "correctMeaning": "Heilung (geistig/spirituell)",
          "context": "مِنَ الْقُرْآنِ — der Quran als Schifa, Heilung für die Gläubigen."
        }
      ]
    },
    {
      "id": 73,
      "word": "خَيْر",
      "root": "خ-ي-ر",
      "meanings": [
        "Gutes/das Gute",
        "besser (Komparativ)",
        "Vermögen/Reichtum"
      ],
      "exercises": [
        {
          "ref": "2:180",
          "arabic": "كُتِبَ عَلَيْكُمْ إِذَا حَضَرَ أَحَدَكُمُ الْمَوْتُ إِن تَرَكَ خَيْرًا",
          "correctMeaning": "Vermögen/Reichtum",
          "context": "إِن تَرَكَ خَيْرًا — wenn er Vermögen hinterlaesst. Im Erbrechts-Kontext = materieller Besitz."
        },
        {
          "ref": "2:184",
          "arabic": "وَأَن تَصُومُوا خَيْرٌ لَّكُمْ",
          "correctMeaning": "besser (Komparativ)",
          "context": "خَيْرٌ لَّكُمْ — Fasten ist besser für euch. Vergleich."
        },
        {
          "ref": "3:26",
          "arabic": "بِيَدِكَ الْخَيْرُ إِنَّكَ عَلَىٰ كُلِّ شَيْءٍ قَدِيرٌ",
          "correctMeaning": "das Gute (allgemein)",
          "context": "بِيَدِكَ الْخَيْرُ — in deiner Hand ist das Gute."
        },
        {
          "ref": "100:8",
          "arabic": "وَإِنَّهُ لِحُبِّ الْخَيْرِ لَشَدِيدٌ",
          "correctMeaning": "Reichtum/Besitz",
          "context": "لِحُبِّ الْخَيْرِ (aus Liebe zum Reichtum) — خَيْر hier = materieller Reichtum."
        }
      ]
    },
    {
      "id": 74,
      "word": "شَرّ",
      "root": "ش-ر-ر",
      "meanings": [
        "Uebel/Böses",
        "schlimmer (Komparativ)",
        "Schaden/Unheil"
      ],
      "exercises": [
        {
          "ref": "113:2",
          "arabic": "مِن شَرِّ مَا خَلَقَ",
          "correctMeaning": "Uebel/Böses",
          "context": "مِن شَرِّ (vor dem Uebel) — Zufluchtsuche vor dem Uebel des Geschaffenen."
        },
        {
          "ref": "2:216",
          "arabic": "وَعَسَىٰ أَن تُحِبُّوا شَيْئًا وَهُوَ شَرٌّ لَّكُمْ",
          "correctMeaning": "schlecht/schaedlich (für euch)",
          "context": "شَرٌّ لَّكُمْ — etwas ist schlecht/schaedlich für euch, obwohl ihr es liebt."
        },
        {
          "ref": "8:22",
          "arabic": "إِنَّ شَرَّ الدَّوَابِّ عِندَ اللَّهِ الصُّمُّ الْبُكْمُ",
          "correctMeaning": "die Schlimmsten (Superlativ)",
          "context": "شَرَّ الدَّوَابِّ — die schlimmsten der Kreaturen bei Gott."
        },
        {
          "ref": "98:6",
          "arabic": "أُولَٰئِكَ هُمْ شَرُّ الْبَرِيَّةِ",
          "correctMeaning": "die Schlimmsten (Superlativ)",
          "context": "شَرُّ الْبَرِيَّةِ — die Schlimmsten der Geschöpfe."
        }
      ]
    },
    {
      "id": 75,
      "word": "رَبّ",
      "root": "ر-ب-ب",
      "meanings": [
        "Herr/Gebieter",
        "Erzieher/Aufzieher",
        "Besitzer/Eigentuemer",
        "Versorger"
      ],
      "exercises": [
        {
          "ref": "1:2",
          "arabic": "الْحَمْدُ لِلَّهِ رَبِّ الْعَالَمِينَ",
          "correctMeaning": "Herr/Gebieter",
          "context": "رَبِّ الْعَالَمِينَ — Herr aller Welten/Geschöpfe."
        },
        {
          "ref": "12:42",
          "arabic": "اذْكُرْنِي عِندَ رَبِّكَ فَأَنسَاهُ الشَّيْطَانُ ذِكْرَ رَبِّهِ",
          "correctMeaning": "Herr/Gebieter (irdisch: König)",
          "context": "عِندَ رَبِّكَ — erwähne mich bei deinem Herrn (dem König Aegyptens)."
        },
        {
          "ref": "26:18",
          "arabic": "قَالَ أَلَمْ نُرَبِّكَ فِينَا وَلِيدًا",
          "correctMeaning": "aufziehen/erziehen",
          "context": "نُرَبِّكَ (II. Stamm: wir haben dich aufgezogen) — die Wurzel ر-ب-ب im Sinne von Erziehung."
        },
        {
          "ref": "17:24",
          "arabic": "وَقُل رَّبِّ ارْحَمْهُمَا كَمَا رَبَّيَانِي صَغِيرًا",
          "correctMeaning": "aufziehen/versorgen",
          "context": "رَبَّيَانِي صَغِيرًا (sie zogen mich klein auf) — Eltern als رَبّ im Sinne von Erziehern."
        }
      ]
    },
    {
      "id": 76,
      "word": "عِبَادَة",
      "root": "ع-ب-د",
      "meanings": [
        "Anbetung/Verehrung",
        "Dienst/Gehorsamkeit",
        "Unterwerfung"
      ],
      "exercises": [
        {
          "ref": "1:5",
          "arabic": "إِيَّاكَ نَعْبُدُ وَإِيَّاكَ نَسْتَعِينُ",
          "correctMeaning": "anbeten/verehren",
          "context": "نَعْبُدُ — vorangestelltes Objekt (إِيَّاكَ) + Verb: Dich dienen wir (Taqdīm)."
        },
        {
          "ref": "19:65",
          "arabic": "رَبُّ السَّمَاوَاتِ وَالْأَرْضِ وَمَا بَيْنَهُمَا فَاعْبُدْهُ وَاصْطَبِرْ لِعِبَادَتِهِ",
          "correctMeaning": "Anbetung/Dienst",
          "context": "وَاصْطَبِرْ لِعِبَادَتِهِ (und sei standhaft in seinem Dienst) — ausdauernde Anbetung."
        },
        {
          "ref": "36:60",
          "arabic": "أَلَمْ أَعْهَدْ إِلَيْكُمْ يَا بَنِي آدَمَ أَن لَّا تَعْبُدُوا الشَّيْطَانَ",
          "correctMeaning": "gehorchen/sich unterwerfen",
          "context": "لَّا تَعْبُدُوا الشَّيْطَانَ — dem Satan nicht gehorchen/sich nicht unterwerfen. Nicht Anbetung im engeren Sinne, sondern Unterwerfung."
        },
        {
          "ref": "51:56",
          "arabic": "وَمَا خَلَقْتُ الْجِنَّ وَالْإِنسَ إِلَّا لِيَعْبُدُونِ",
          "correctMeaning": "anbeten/dienen",
          "context": "إِلَّا لِيَعْبُدُونِ — der Zweck der Schöpfung: Anbetung/Dienst."
        }
      ]
    },
    {
      "id": 77,
      "word": "نَبَأ",
      "root": "ن-ب-ا",
      "meanings": [
        "Nachricht/Kunde",
        "wichtige Nachricht/Botschaft",
        "Geschichte/Bericht"
      ],
      "exercises": [
        {
          "ref": "6:34",
          "arabic": "وَلَقَدْ جَاءَكَ مِن نَّبَإِ الْمُرْسَلِينَ",
          "correctMeaning": "Geschichte/Bericht",
          "context": "نَّبَإِ الْمُرْسَلِينَ — Berichte über die frueheren Gesandten."
        },
        {
          "ref": "78:2",
          "arabic": "عَنِ النَّبَإِ الْعَظِيمِ",
          "correctMeaning": "wichtige Nachricht/Botschaft",
          "context": "النَّبَإِ الْعَظِيمِ (die gewaltige Nachricht) — bezieht sich auf die Auferstehung oder den Quran."
        },
        {
          "ref": "49:6",
          "arabic": "يَا أَيُّهَا الَّذِينَ آمَنُوا إِن جَاءَكُمْ فَاسِقٌ بِنَبَإٍ فَتَبَيَّنُوا",
          "correctMeaning": "Nachricht/Kunde",
          "context": "بِنَبَإٍ (mit einer Nachricht) — eine zu verifizierende Nachricht von einem Frevler."
        },
        {
          "ref": "26:69",
          "arabic": "وَاتْلُ عَلَيْهِمْ نَبَأَ إِبْرَاهِيمَ",
          "correctMeaning": "Geschichte/Bericht",
          "context": "وَاتْلُ (trag vor) + نَبَأَ إِبْرَاهِيمَ — die Geschichte Ibrahims vortragen."
        }
      ]
    },
    {
      "id": 78,
      "word": "حَدِيث",
      "root": "ح-د-ث",
      "meanings": [
        "Rede/Gespräch",
        "Erzählung/Geschichte",
        "Neuigkeit/neue Sache"
      ],
      "exercises": [
        {
          "ref": "4:42",
          "arabic": "وَمَنْ أَصْدَقُ مِنَ اللَّهِ حَدِيثًا",
          "correctMeaning": "Rede/Aussage",
          "context": "أَصْدَقُ حَدِيثًا (wahrhaftiger in der Rede) — Gottes Rede als die wahrhaftigste."
        },
        {
          "ref": "20:9",
          "arabic": "وَهَلْ أَتَاكَ حَدِيثُ مُوسَىٰ",
          "correctMeaning": "Geschichte/Erzählung",
          "context": "حَدِيثُ مُوسَىٰ — die Geschichte Moses, die erzählt wird."
        },
        {
          "ref": "12:111",
          "arabic": "مَا كَانَ حَدِيثًا يُفْتَرَىٰ",
          "correctMeaning": "Erzählung/Bericht",
          "context": "حَدِيثًا يُفْتَرَىٰ (eine erfundene Erzählung) — der Quran ist keine erfundene Geschichte."
        },
        {
          "ref": "66:3",
          "arabic": "وَإِذْ أَسَرَّ النَّبِيُّ إِلَىٰ بَعْضِ أَزْوَاجِهِ حَدِيثًا",
          "correctMeaning": "Gespräch/vertrauliche Rede",
          "context": "أَسَرَّ (er vertraute an) — ein vertrauliches Gespräch."
        },
        {
          "ref": "93:11",
          "arabic": "وَأَمَّا بِنِعْمَةِ رَبِّكَ فَحَدِّثْ",
          "correctMeaning": "berichten/erzählen (Verb)",
          "context": "فَحَدِّثْ (so berichte!) — II. Stamm als Imperativ: über Gottes Gabe erzählen."
        }
      ]
    }
  ]
}